{"file":{"path":"D:\\ARMOR\\PDF\\4_5857242657574620109.pdf","name":"4_5857242657574620109.pdf","ext":".pdf","length":797285,"dir":"D:\\ARMOR\\PDF","creation":"2021-11-14T13:14:20","lastaccess":"2021-11-16T23:22:20","lastwrite":"2021-08-27T13:10:41"},"hash":{"md5":"422EDA2857F8CFD61B3851122027C65F","sha1":"1B28FB235952D1BC370D0FEF05BF7EAC7CFD4349"},"tika":{"content-type":"application/pdf","creation-date":"2012-10-17T20:39:14","last-modified":"2012-10-17T20:39:14Z","last-save-date":"2012-10-17T20:39:14Z","x-parsed-by":["org.apache.tika.parser.DefaultParser","org.apache.tika.parser.pdf.PDFParser"],"access_permission.assemble_document":true,"access_permission.can_modify":true,"access_permission.can_print":true,"access_permission.can_print_degraded":true,"access_permission.extract_content":true,"access_permission.extract_for_accessibility":true,"access_permission.fill_in_form":true,"access_permission.modify_annotations":true,"created":"2012-10-17T20:39:14","date":"2012-10-17T20:39:14Z","dc.format":"application/pdf; version=1.7","dcterms.created":"2012-10-17T20:39:14Z","dcterms.modified":"2012-10-17T20:39:14Z","meta.creation-date":"2012-10-17T20:39:14Z","meta.save-date":"2012-10-17T20:39:14Z","modified":"2012-10-17T20:39:14Z","pdf.pdfversion":"1.7","pdf.charsperpage":["519","444","550","2399","1410","1280","2285","2326","2719","2420","2102","1714","2038","2168","2027","2717","2962","3050","1280","2346","1796","2111","1774","1230","2316","2655","2212","2439","2416","2337","2363","1591","1646","2353","2243","1975","2161","2333","2275","2170","1299","1823","2118","2308","2808","1913","398"],"pdf.docinfo.created":"2012-10-17T20:39:14Z","pdf.docinfo.modified":"2012-10-17T20:39:14Z","pdf.docinfo.producer":"PDFTron PDFNet","pdf.encrypted":false,"pdf.hasmarkedcontent":false,"pdf.hasxfa":false,"pdf.hasxmp":false,"pdf.unmappedunicodecharsperpage":["0","0","0","0","0","0","0","0","0","0","0","0","0","0","0","0","0","0","0","0","0","0","0","0","0","0","0","0","0","0","0","0","0","0","0","0","0","0","0","0","0","0","0","0","0","0","0"],"producer":"PDFTron PDFNet"},"pdf":{"info":{"creationdate_error":"D:20121017203914Z00'00'","moddate":"D:20121017203914Z00'00'","producer":"PDFTron PDFNet"},"pdfversion":"7","tampered":false,"appendable":false,"cryptomode":-1},"sha256":"06D7946241F5ABD5A84E1B37B193D037E9273302F6FC0A3ABEFAC5FC6A972F61","clean.language":"ru","clean.pageCount":"47"}