{"file":{"path":"D:\\YANDEX_DOWNLOADS\\__OK\\Kitaplık\\Karikatür\\Hibir-dergisi-sayi-6.pdf","name":"Hibir-dergisi-sayi-6.pdf","ext":".pdf","length":3552540,"dir":"D:\\YANDEX_DOWNLOADS\\__OK\\Kitaplık\\Karikatür","creation":"2020-12-19T11:27:03","lastaccess":"2020-12-26T00:00:01","lastwrite":"2020-12-19T11:27:10"},"hash":{"md5":"46885559DC4936664064172EE00D289F","sha1":"D87E25003A68070076D46AF1C6C03F5AF94A9818"},"tika":{"content-type":"application/pdf","creation-date":"2010-12-13T19:19:09","last-modified":"2010-12-13T19:19:09","last-save-date":"2010-12-13T19:19:09","x-parsed-by":["org.apache.tika.parser.DefaultParser","org.apache.tika.parser.pdf.PDFParser"],"access_permission.assemble_document":"true","access_permission.can_modify":"true","access_permission.can_print":"true","access_permission.can_print_degraded":"true","access_permission.extract_content":"true","access_permission.extract_for_accessibility":"true","access_permission.fill_in_form":"true","access_permission.modify_annotations":"true","created":"2010-12-13T19:19:09","date":"2010-12-13T19:19:09","dc.format":"application/pdf; version=1.6","dcterms.created":"2010-12-13T19:19:09","dcterms.modified":"2010-12-13T19:19:09","meta.creation-date":"2010-12-13T19:19:09","meta.save-date":"2010-12-13T19:19:09","modified":"2010-12-13T19:19:09","pdf.pdfversion":"2020-01-06T00:00:00","pdf.charsperpage":["0","0","0","0","0","0","0","0","0","0","0","0","0","0","0","0"],"pdf.docinfo.created":"2010-12-13T19:19:09","pdf.docinfo.creator_tool":"Adobe Acrobat 9.3","pdf.docinfo.modified":"2010-12-13T19:19:09","pdf.docinfo.producer":"Adobe Acrobat 9.3 Image Conversion Plug-in","pdf.encrypted":"false","pdf.hasmarkedcontent":"true","pdf.hasxfa":"false","pdf.hasxmp":"true","pdf.producer":"Adobe Acrobat 9.3 Image Conversion Plug-in","pdf.unmappedunicodecharsperpage":["0","0","0","0","0","0","0","0","0","0","0","0","0","0","0","0"],"producer":"Adobe Acrobat 9.3 Image Conversion Plug-in","xmp.createdate":"2010-12-13T21:19:09","xmp.creatortool":"Adobe Acrobat 9.3","xmp.metadatadate":"2010-12-13T21:19:09","xmp.modifydate":"2010-12-13T21:19:09","xmpmm.documentid":"uuid:d6975cf3-61d3-4707-916f-111c928169f3"},"pdf":{"info":{"creationdate":"D:20101213211909+02'00'","moddate":"D:20101213211909+02'00'","producer":"Adobe Acrobat 9.3 Image Conversion Plug-in"},"pdfversion":"6","metadata":{"modifydate":["12/13/2010 11:19:09 PM"],"createdate":["12/13/2010 11:19:09 PM"],"metadatadate":["12/13/2010 11:19:09 PM"],"creatortool":["Adobe Acrobat 9.3"],"format":["application/pdf"],"documentid":["uuid:d6975cf3-61d3-4707-916f-111c928169f3"],"instanceid":["uuid:e6ab634a-3a9f-4447-a8f7-e87e489b6772"],"producer":["Adobe Acrobat 9.3 Image Conversion Plug-in"]},"tampered":false,"appendable":false,"cryptomode":-1},"sha256":"11C46D0850C0413603FD93FE1F7A5DA11D9708C6EF6B5CB2E8F3AFBAAED9110D","clean.language":"tl","clean.pageCount":"16","clean.creator":"adobe acrobat 9.3"}