{"file":{"path":"D:\\SHARED\\Tamamdir\\___AZ_CORPUS\\a3518d33c32e4edc6407320503d905c2.pdf","name":"a3518d33c32e4edc6407320503d905c2.pdf","ext":".pdf","length":24235465,"dir":"D:\\SHARED\\Tamamdir\\___AZ_CORPUS","creation":"2020-08-13T10:01:43","lastaccess":"2020-12-17T01:27:19","lastwrite":"2015-05-25T09:55:04"},"hash":{"md5":"A3518D33C32E4EDC6407320503D905C2","sha1":"948DC1921C965A5847C6B4C076F8F11FFC0A1132"},"tika":{"content-type":"application/pdf","creation-date":"2012-10-20T08:28:05","last-modified":"2012-10-26T07:25:48","last-save-date":"2012-10-26T07:25:48","x-parsed-by":["org.apache.tika.parser.DefaultParser","org.apache.tika.parser.pdf.PDFParser"],"access_permission.assemble_document":"true","access_permission.can_modify":"true","access_permission.can_print":"true","access_permission.can_print_degraded":"true","access_permission.extract_content":"true","access_permission.extract_for_accessibility":"true","access_permission.fill_in_form":"true","access_permission.modify_annotations":"true","created":"2012-10-20T08:28:05","date":"2012-10-26T07:25:48","dc.format":"application/pdf; version=1.4","dcterms.created":"2012-10-20T08:28:05","dcterms.modified":"2012-10-26T07:25:48","meta.creation-date":"2012-10-20T08:28:05","meta.save-date":"2012-10-26T07:25:48","modified":"2012-10-26T07:25:48","pdf.pdfversion":"2020-01-04T00:00:00","pdf.charsperpage":["98","415","1654","1850","1764","2040","1470","1900","2098","1987","2050","2011","1995","1913","1547","1631","1587","1521","1611","1411","1515","1589","1367","2022","1954","1830","1875","59","1759","1900","1942","1961","2048","1760","2137","1938","1981","2075","2027","1998","1787","1893","1910","1781","1762","2054","2106","2077","1961","38","1996","1872","1888","1884","754","753","791","1191","2029","1817","2047","1521","652","1227","2091","1955","39","2074","1962","36","1809","2026","32","2079","1897","1899","1726","1504","1581","1968","1379","1763","1968","1835","1843","1911","1825","2000","3","1","19","25","23","20","20","25","23","22","77","96","112","1","0","1","1819","1955","39","1816","2022","1534","1678","1027","495","1020","1048","1360","338","390","299","260","121","164","232","181","1244","1481","1623","1406","1365","1521","1416","1484","1498","1466","1821","1606","2003","2121","1839","982","1016","466","1459","80"],"pdf.docinfo.created":"2012-10-20T08:28:05","pdf.docinfo.creator_tool":"Adobe InDesign CS5 (7.0)","pdf.docinfo.modified":"2012-10-26T07:25:48","pdf.docinfo.producer":"Adobe PDF Library 9.9","pdf.docinfo.trapped":"False","pdf.encrypted":"false","pdf.hasmarkedcontent":"true","pdf.hasxfa":"false","pdf.hasxmp":"true","pdf.producer":"Adobe PDF Library 9.9","pdf.unmappedunicodecharsperpage":["0","0","0","0","0","0","0","0","0","0","0","0","0","0","0","0","0","0","0","0","0","0","0","0","0","0","0","0","0","0","0","0","0","0","0","0","0","0","0","0","0","0","0","0","0","0","0","0","0","0","0","0","0","0","0","0","0","0","0","0","0","0","0","0","0","0","0","0","0","0","0","0","0","0","0","0","0","0","0","0","0","0","0","0","0","0","0","0","0","0","0","0","0","0","0","0","0","0","0","0","0","0","0","0","0","0","0","0","0","0","0","0","0","0","0","0","0","0","0","0","0","0","0","0","0","0","0","0","0","0","0","0","0","0","0","0","0","0","0","0","0","0","0","0"],"producer":"Adobe PDF Library 9.9","trapped":"False","xmp.createdate":"2012-10-20T13:28:05","xmp.creatortool":"Adobe InDesign CS5 (7.0)","xmp.metadatadate":"2012-10-26T12:25:48","xmp.modifydate":"2012-10-26T12:25:48","xmpmm.derivedfrom.documentid":"xmp.did:D5477FF08508E211BE67E2C097ABABFB","xmpmm.derivedfrom.instanceid":"xmp.iid:0642402D440EE211A472D536B3B35FD0","xmpmm.documentid":"xmp.did:0742402D440EE211A472D536B3B35FD0","xmpmm.history.action":["saved","saved","saved","saved","saved","saved","saved","saved","saved","saved","saved","saved","saved","saved","saved","saved","saved","saved","saved","saved","saved","saved","saved","saved","saved","saved","saved","saved","saved","saved","saved","saved","saved","saved","saved","saved","saved","saved","saved","saved","saved","saved","saved","saved","saved","saved","saved","saved","saved","saved","saved","saved","saved","saved","saved","saved","saved","saved","saved","saved","saved","saved","saved","saved","saved","saved","saved","saved","saved","saved","saved","saved","saved","saved","saved","saved","saved","saved","saved","saved","saved","saved","saved","saved","saved","saved","saved","saved","saved","saved","saved","saved","saved","saved"],"xmpmm.history.instanceid":["xmp.iid:421803F42A0CE0119683C3BEF0394F10","xmp.iid:431803F42A0CE0119683C3BEF0394F10","xmp.iid:D9294CB215B1E011A749C8574FE6D5B5","xmp.iid:CDCC115F6CBEE011AEF4E5BF4D8B9EA1","xmp.iid:D4CA46517EBEE011975C980A3A7167D3","xmp.iid:69C565AFAFE3E111BF99A72B018DCF7C","xmp.iid:6BC565AFAFE3E111BF99A72B018DCF7C","xmp.iid:6CC565AFAFE3E111BF99A72B018DCF7C","xmp.iid:6DC565AFAFE3E111BF99A72B018DCF7C","xmp.iid:6EC565AFAFE3E111BF99A72B018DCF7C","xmp.iid:6FC565AFAFE3E111BF99A72B018DCF7C","xmp.iid:70C565AFAFE3E111BF99A72B018DCF7C","xmp.iid:71C565AFAFE3E111BF99A72B018DCF7C","xmp.iid:867C118414E5E111A3C9DE6BD2F848E1","xmp.iid:877C118414E5E111A3C9DE6BD2F848E1","xmp.iid:887C118414E5E111A3C9DE6BD2F848E1","xmp.iid:897C118414E5E111A3C9DE6BD2F848E1","xmp.iid:8A7C118414E5E111A3C9DE6BD2F848E1","xmp.iid:8B7C118414E5E111A3C9DE6BD2F848E1","xmp.iid:0FD024A4F9E8E111B3E6AB017A4B1ADD","xmp.iid:415E611413E9E1118945E017C5B428BF","xmp.iid:425E611413E9E1118945E017C5B428BF","xmp.iid:435E611413E9E1118945E017C5B428BF","xmp.iid:445E611413E9E1118945E017C5B428BF","xmp.iid:455E611413E9E1118945E017C5B428BF","xmp.iid:465E611413E9E1118945E017C5B428BF","xmp.iid:475E611413E9E1118945E017C5B428BF","xmp.iid:485E611413E9E1118945E017C5B428BF","xmp.iid:495E611413E9E1118945E017C5B428BF","xmp.iid:EF2CF4A003E9E1119CFEA42A2BD6714D","xmp.iid:F12CF4A003E9E1119CFEA42A2BD6714D","xmp.iid:B8F6A7012DE9E111809CE65A044A27F6","xmp.iid:B9F6A7012DE9E111809CE65A044A27F6","xmp.iid:BAF6A7012DE9E111809CE65A044A27F6","xmp.iid:BBF6A7012DE9E111809CE65A044A27F6","xmp.iid:BCF6A7012DE9E111809CE65A044A27F6","xmp.iid:BDF6A7012DE9E111809CE65A044A27F6","xmp.iid:BEF6A7012DE9E111809CE65A044A27F6","xmp.iid:BFF6A7012DE9E111809CE65A044A27F6","xmp.iid:C0F6A7012DE9E111809CE65A044A27F6","xmp.iid:371AD5F8C7FFE1119770C98A43309C51","xmp.iid:381AD5F8C7FFE1119770C98A43309C51","xmp.iid:391AD5F8C7FFE1119770C98A43309C51","xmp.iid:3A1AD5F8C7FFE1119770C98A43309C51","xmp.iid:3B1AD5F8C7FFE1119770C98A43309C51","xmp.iid:3C1AD5F8C7FFE1119770C98A43309C51","xmp.iid:FABA850C8500E2118CAF841AEE1F9604","xmp.iid:FBBA850C8500E2118CAF841AEE1F9604","xmp.iid:99F63E9E5205E211BC86BCCC966222AB","xmp.iid:9AF63E9E5205E211BC86BCCC966222AB","xmp.iid:9BF63E9E5205E211BC86BCCC966222AB","xmp.iid:09363DF70207E211B2EADA36E9A9DB37","xmp.iid:0A363DF70207E211B2EADA36E9A9DB37","xmp.iid:0C363DF70207E211B2EADA36E9A9DB37","xmp.iid:D6C806601107E2119447ED03F1FB3907","xmp.iid:D7C806601107E2119447ED03F1FB3907","xmp.iid:8C93BC31DE07E211A34E84F24DE3F40B","xmp.iid:D6477FF08508E211BE67E2C097ABABFB","xmp.iid:D7477FF08508E211BE67E2C097ABABFB","xmp.iid:D8477FF08508E211BE67E2C097ABABFB","xmp.iid:0642402D440EE211A472D536B3B35FD0","xmp.iid:0742402D440EE211A472D536B3B35FD0","xmp.iid:0842402D440EE211A472D536B3B35FD0","xmp.iid:0942402D440EE211A472D536B3B35FD0","xmp.iid:0B42402D440EE211A472D536B3B35FD0","xmp.iid:0F42402D440EE211A472D536B3B35FD0","xmp.iid:0A45D24A4E0EE211A472D536B3B35FD0","xmp.iid:0F45D24A4E0EE211A472D536B3B35FD0","xmp.iid:9EC9E881520EE211A472D536B3B35FD0","xmp.iid:A3C9E881520EE211A472D536B3B35FD0","xmp.iid:52CD5A89550EE211A472D536B3B35FD0","xmp.iid:6BF2C658E30EE211A534A80C9AAE1A95","xmp.iid:BE07E0FAA712E211BB37F602F991293D","xmp.iid:C307E0FAA712E211BB37F602F991293D","xmp.iid:0BABBAC8AE12E211BB37F602F991293D","xmp.iid:736E5265AF12E211BB37F602F991293D","xmp.iid:CCC0C15DB112E211BB37F602F991293D","xmp.iid:6BF46227B512E211BB37F602F991293D","xmp.iid:B016B027AE13E211AC4EF6796C4F3A49","xmp.iid:42D3A6E5AF13E2118E4F8A2ADF6989EC","xmp.iid:07040E3EB113E2118E4F8A2ADF6989EC","xmp.iid:9CF8637EB113E2118E4F8A2ADF6989EC","xmp.iid:F6FB0C5BB313E2118E4F8A2ADF6989EC","xmp.iid:DBE9B747B413E2118E4F8A2ADF6989EC","xmp.iid:9A6CB5AAB413E2118E4F8A2ADF6989EC","xmp.iid:F32657566E14E211BD039A0765084D93","xmp.iid:1A68B5ABD716E2118B50AF4ABA2AC0B0","xmp.iid:EA64C06FD816E2118B50AF4ABA2AC0B0","xmp.iid:C677AFE8D816E211A947B1B584DFC922","xmp.iid:3D7543759817E21187CA924CC36B8837","xmp.iid:7A60B59B9817E21187CA924CC36B8837","xmp.iid:C36F315F9917E21187CA924CC36B8837","xmp.iid:72F9E30A3418E211826A9D363868C5CC","xmp.iid:7FF109F28F1AE211B194CD84BA27B53C"],"xmpmm.history.softwareagent":["Adobe InDesign 7.0","Adobe InDesign 7.0","Adobe InDesign 7.0","Adobe InDesign 7.0","Adobe InDesign 7.0","Adobe InDesign 7.0","Adobe InDesign 7.0","Adobe InDesign 7.0","Adobe InDesign 7.0","Adobe InDesign 7.0","Adobe InDesign 7.0","Adobe InDesign 7.0","Adobe InDesign 7.0","Adobe InDesign 7.0","Adobe InDesign 7.0","Adobe InDesign 7.0","Adobe InDesign 7.0","Adobe InDesign 7.0","Adobe InDesign 7.0","Adobe InDesign 7.0","Adobe InDesign 7.0","Adobe InDesign 7.0","Adobe InDesign 7.0","Adobe InDesign 7.0","Adobe InDesign 7.0","Adobe InDesign 7.0","Adobe InDesign 7.0","Adobe InDesign 7.0","Adobe InDesign 7.0","Adobe InDesign 7.0","Adobe InDesign 7.0","Adobe InDesign 7.0","Adobe InDesign 7.0","Adobe InDesign 7.0","Adobe InDesign 7.0","Adobe InDesign 7.0","Adobe InDesign 7.0","Adobe InDesign 7.0","Adobe InDesign 7.0","Adobe InDesign 7.0","Adobe InDesign 7.0","Adobe InDesign 7.0","Adobe InDesign 7.0","Adobe InDesign 7.0","Adobe InDesign 7.0","Adobe InDesign 7.0","Adobe InDesign 7.0","Adobe InDesign 7.0","Adobe InDesign 7.0","Adobe InDesign 7.0","Adobe InDesign 7.0","Adobe InDesign CS6 (Windows)","Adobe InDesign CS6 (Windows)","Adobe InDesign CS6 (Windows)","Adobe InDesign CS6 (Windows)","Adobe InDesign CS6 (Windows)","Adobe InDesign CS6 (Windows)","Adobe InDesign 7.0","Adobe InDesign 7.0","Adobe InDesign 7.0","Adobe InDesign 7.0","Adobe InDesign 7.0","Adobe InDesign 7.0","Adobe InDesign 7.0","Adobe InDesign 7.0","Adobe InDesign 7.0","Adobe InDesign 7.0","Adobe InDesign 7.0","Adobe InDesign 7.0","Adobe InDesign 7.0","Adobe InDesign 7.0","Adobe InDesign 7.0","Adobe InDesign 7.0","Adobe InDesign 7.0","Adobe InDesign 7.0","Adobe InDesign 7.0","Adobe InDesign 7.0","Adobe InDesign 7.0","Adobe InDesign 7.0","Adobe InDesign 7.0","Adobe InDesign 7.0","Adobe InDesign 7.0","Adobe InDesign 7.0","Adobe InDesign 7.0","Adobe InDesign 7.0","Adobe InDesign 7.0","Adobe InDesign 7.0","Adobe InDesign 7.0","Adobe InDesign 7.0","Adobe InDesign 7.0","Adobe InDesign 7.0","Adobe InDesign 7.0","Adobe InDesign 7.0","Adobe InDesign 7.0"],"xmpmm.history.when":["2010-12-20T15:19:04Z","2010-12-20T15:19:04Z","2011-07-18T13:12:36Z","2011-08-04T12:35:48Z","2011-08-04T14:44:15Z","2012-08-11T17:25:49Z","2012-08-11T17:25:49Z","2012-08-11T17:35:32Z","2012-08-11T17:38:28Z","2012-08-11T17:53:39Z","2012-08-11T18:07:49Z","2012-08-11T18:08:39Z","2012-08-11T18:11:01Z","2012-08-13T12:21:03Z","2012-08-13T12:36:12Z","2012-08-13T12:40:59Z","2012-08-13T12:45:46Z","2012-08-13T12:46:54Z","2012-08-13T12:53:11Z","2012-08-18T10:57:49Z","2012-08-18T13:59:55Z","2012-08-18T14:25:22Z","2012-08-18T14:27:16Z","2012-08-18T14:37:57Z","2012-08-18T14:38:31Z","2012-08-18T14:51:00Z","2012-08-18T14:53:34Z","2012-08-18T14:56:00Z","2012-08-18T15:00:37Z","2012-08-18T15:18:11Z","2012-08-18T15:33:47Z","2012-08-18T17:05:30Z","2012-08-18T17:06:09Z","2012-08-18T17:07:20Z","2012-08-18T17:07:49Z","2012-08-18T17:09:06Z","2012-08-18T17:09:57Z","2012-08-18T17:10:21Z","2012-08-18T17:10:59Z","2012-08-18T17:12:46Z","2012-09-16T11:30:13Z","2012-09-16T11:41:05Z","2012-09-16T11:52:36Z","2012-09-16T11:59:52Z","2012-09-16T12:00:54Z","2012-09-16T12:11:47Z","2012-09-17T10:03:41Z","2012-09-17T10:07:02Z","2012-09-23T12:45:17Z","2012-09-23T13:00:21Z","2012-09-23T13:02:55Z","2012-09-25T16:20:09Z","2012-09-25T16:20:09Z","2012-09-25T16:25:44Z","2012-09-25T18:03:18Z","2012-09-25T18:03:18Z","2012-09-26T18:29:27Z","2012-09-27T14:31:13Z","2012-09-27T14:31:13Z","2012-09-27T14:33:59Z","2012-10-04T21:54:35Z","2012-10-04T21:54:35Z","2012-10-04T22:16:07Z","2012-10-04T22:27:48Z","2012-10-04T22:55:51Z","2012-10-04T23:03:34Z","2012-10-04T23:07:00Z","2012-10-04T23:34:14Z","2012-10-04T23:37:10Z","2012-10-04T23:40:25Z","2012-10-04T23:58:51Z","2012-10-05T16:53:58Z","2012-10-10T11:59:05Z","2012-10-10T12:07:39Z","2012-10-10T12:47:47Z","2012-10-10T12:52:10Z","2012-10-10T13:06:16Z","2012-10-10T13:33:23Z","2012-10-11T19:15:48Z","2012-10-11T19:28:16Z","2012-10-11T19:37:54Z","2012-10-11T19:39:42Z","2012-10-11T19:53:02Z","2012-10-11T19:59:39Z","2012-10-11T20:02:25Z","2012-10-12T18:11:30Z","2012-10-15T19:50:32Z","2012-10-15T19:56:01Z","2012-10-15T19:59:24Z","2012-10-16T18:50:34Z","2012-10-16T18:51:38Z","2012-10-16T18:57:06Z","2012-10-17T13:24:17Z","2012-10-20T13:27:11Z"]},"pdf":{"info":{"creationdate":"D:20121020132805+05'00'","moddate":"D:20121026122548+05'00'","producer":"Adobe PDF Library 9.9","trapped":"False"},"pdfversion":"4","metadata":{"instanceid":["uuid:dc4509d4-c1fd-4cf6-bc96-4eb19c8582ab","xmp.iid:421803F42A0CE0119683C3BEF0394F10","xmp.iid:431803F42A0CE0119683C3BEF0394F10","xmp.iid:D9294CB215B1E011A749C8574FE6D5B5","xmp.iid:CDCC115F6CBEE011AEF4E5BF4D8B9EA1","xmp.iid:D4CA46517EBEE011975C980A3A7167D3","xmp.iid:69C565AFAFE3E111BF99A72B018DCF7C","xmp.iid:6BC565AFAFE3E111BF99A72B018DCF7C","xmp.iid:6CC565AFAFE3E111BF99A72B018DCF7C","xmp.iid:6DC565AFAFE3E111BF99A72B018DCF7C","xmp.iid:6EC565AFAFE3E111BF99A72B018DCF7C","xmp.iid:6FC565AFAFE3E111BF99A72B018DCF7C","xmp.iid:70C565AFAFE3E111BF99A72B018DCF7C","xmp.iid:71C565AFAFE3E111BF99A72B018DCF7C","xmp.iid:867C118414E5E111A3C9DE6BD2F848E1","xmp.iid:877C118414E5E111A3C9DE6BD2F848E1","xmp.iid:887C118414E5E111A3C9DE6BD2F848E1","xmp.iid:897C118414E5E111A3C9DE6BD2F848E1","xmp.iid:8A7C118414E5E111A3C9DE6BD2F848E1","xmp.iid:8B7C118414E5E111A3C9DE6BD2F848E1","xmp.iid:0FD024A4F9E8E111B3E6AB017A4B1ADD","xmp.iid:415E611413E9E1118945E017C5B428BF","xmp.iid:425E611413E9E1118945E017C5B428BF","xmp.iid:435E611413E9E1118945E017C5B428BF","xmp.iid:445E611413E9E1118945E017C5B428BF","xmp.iid:455E611413E9E1118945E017C5B428BF","xmp.iid:465E611413E9E1118945E017C5B428BF","xmp.iid:475E611413E9E1118945E017C5B428BF","xmp.iid:485E611413E9E1118945E017C5B428BF","xmp.iid:495E611413E9E1118945E017C5B428BF","xmp.iid:EF2CF4A003E9E1119CFEA42A2BD6714D","xmp.iid:F12CF4A003E9E1119CFEA42A2BD6714D","xmp.iid:B8F6A7012DE9E111809CE65A044A27F6","xmp.iid:B9F6A7012DE9E111809CE65A044A27F6","xmp.iid:BAF6A7012DE9E111809CE65A044A27F6","xmp.iid:BBF6A7012DE9E111809CE65A044A27F6","xmp.iid:BCF6A7012DE9E111809CE65A044A27F6","xmp.iid:BDF6A7012DE9E111809CE65A044A27F6","xmp.iid:BEF6A7012DE9E111809CE65A044A27F6","xmp.iid:BFF6A7012DE9E111809CE65A044A27F6","xmp.iid:C0F6A7012DE9E111809CE65A044A27F6","xmp.iid:371AD5F8C7FFE1119770C98A43309C51","xmp.iid:381AD5F8C7FFE1119770C98A43309C51","xmp.iid:391AD5F8C7FFE1119770C98A43309C51","xmp.iid:3A1AD5F8C7FFE1119770C98A43309C51","xmp.iid:3B1AD5F8C7FFE1119770C98A43309C51","xmp.iid:3C1AD5F8C7FFE1119770C98A43309C51","xmp.iid:FABA850C8500E2118CAF841AEE1F9604","xmp.iid:FBBA850C8500E2118CAF841AEE1F9604","xmp.iid:99F63E9E5205E211BC86BCCC966222AB","xmp.iid:9AF63E9E5205E211BC86BCCC966222AB","xmp.iid:9BF63E9E5205E211BC86BCCC966222AB","xmp.iid:09363DF70207E211B2EADA36E9A9DB37","xmp.iid:0A363DF70207E211B2EADA36E9A9DB37","xmp.iid:0C363DF70207E211B2EADA36E9A9DB37","xmp.iid:D6C806601107E2119447ED03F1FB3907","xmp.iid:D7C806601107E2119447ED03F1FB3907","xmp.iid:8C93BC31DE07E211A34E84F24DE3F40B","xmp.iid:D6477FF08508E211BE67E2C097ABABFB","xmp.iid:D7477FF08508E211BE67E2C097ABABFB","xmp.iid:D8477FF08508E211BE67E2C097ABABFB","xmp.iid:0642402D440EE211A472D536B3B35FD0","xmp.iid:0742402D440EE211A472D536B3B35FD0","xmp.iid:0842402D440EE211A472D536B3B35FD0","xmp.iid:0942402D440EE211A472D536B3B35FD0","xmp.iid:0B42402D440EE211A472D536B3B35FD0","xmp.iid:0F42402D440EE211A472D536B3B35FD0","xmp.iid:0A45D24A4E0EE211A472D536B3B35FD0","xmp.iid:0F45D24A4E0EE211A472D536B3B35FD0","xmp.iid:9EC9E881520EE211A472D536B3B35FD0","xmp.iid:A3C9E881520EE211A472D536B3B35FD0","xmp.iid:52CD5A89550EE211A472D536B3B35FD0","xmp.iid:6BF2C658E30EE211A534A80C9AAE1A95","xmp.iid:BE07E0FAA712E211BB37F602F991293D","xmp.iid:C307E0FAA712E211BB37F602F991293D","xmp.iid:0BABBAC8AE12E211BB37F602F991293D","xmp.iid:736E5265AF12E211BB37F602F991293D","xmp.iid:CCC0C15DB112E211BB37F602F991293D","xmp.iid:6BF46227B512E211BB37F602F991293D","xmp.iid:B016B027AE13E211AC4EF6796C4F3A49","xmp.iid:42D3A6E5AF13E2118E4F8A2ADF6989EC","xmp.iid:07040E3EB113E2118E4F8A2ADF6989EC","xmp.iid:9CF8637EB113E2118E4F8A2ADF6989EC","xmp.iid:F6FB0C5BB313E2118E4F8A2ADF6989EC","xmp.iid:DBE9B747B413E2118E4F8A2ADF6989EC","xmp.iid:9A6CB5AAB413E2118E4F8A2ADF6989EC","xmp.iid:F32657566E14E211BD039A0765084D93","xmp.iid:1A68B5ABD716E2118B50AF4ABA2AC0B0","xmp.iid:EA64C06FD816E2118B50AF4ABA2AC0B0","xmp.iid:C677AFE8D816E211A947B1B584DFC922","xmp.iid:3D7543759817E21187CA924CC36B8837","xmp.iid:7A60B59B9817E21187CA924CC36B8837","xmp.iid:C36F315F9917E21187CA924CC36B8837","xmp.iid:72F9E30A3418E211826A9D363868C5CC","xmp.iid:7FF109F28F1AE211B194CD84BA27B53C"],"originaldocumentid":["adobe:docid:indd:3b76cfe2-c54a-11df-8e93-c112baa796fa"],"documentid":["xmp.did:0742402D440EE211A472D536B3B35FD0","xmp.did:D5477FF08508E211BE67E2C097ABABFB"],"renditionclass":["proof:pdf","default"],"action":["saved"],"when":["12/20/2010 3:19:04 AM","7/18/2011 1:12:36 AM","8/4/2011 12:35:48 AM","8/4/2011 2:44:15 AM","8/11/2012 5:25:49 AM","8/11/2012 5:35:32 AM","8/11/2012 5:38:28 AM","8/11/2012 5:53:39 AM","8/11/2012 6:07:49 AM","8/11/2012 6:08:39 AM","8/11/2012 6:11:01 AM","8/13/2012 12:21:03 AM","8/13/2012 12:36:12 AM","8/13/2012 12:40:59 AM","8/13/2012 12:45:46 AM","8/13/2012 12:46:54 AM","8/13/2012 12:53:11 AM","8/17/2012 10:57:49 PM","8/18/2012 1:59:55 AM","8/18/2012 2:25:22 AM","8/18/2012 2:27:16 AM","8/18/2012 2:37:57 AM","8/18/2012 2:38:31 AM","8/18/2012 2:51:00 PM","8/18/2012 2:53:34 AM","8/18/2012 2:56:00 PM","8/18/2012 3:00:37 AM","8/18/2012 3:18:11 AM","8/18/2012 3:33:47 AM","8/18/2012 5:05:30 AM","8/18/2012 5:06:09 AM","8/18/2012 5:07:20 AM","8/18/2012 5:07:49 AM","8/18/2012 5:09:06 AM","8/18/2012 5:09:57 AM","8/18/2012 5:10:21 AM","8/18/2012 5:10:59 AM","8/18/2012 5:12:46 AM","9/15/2012 11:30:13 PM","9/15/2012 11:41:05 PM","9/15/2012 11:52:36 PM","9/15/2012 11:59:52 PM","9/16/2012 12:00:54 AM","9/16/2012 12:11:47 AM","9/16/2012 10:03:41 PM","9/16/2012 10:07:02 PM","9/23/2012 12:45:17 AM","9/23/2012 1:00:21 AM","9/23/2012 1:02:55 AM","9/25/2012 4:20:09 AM","9/25/2012 4:25:44 AM","9/25/2012 6:03:18 AM","9/26/2012 6:29:27 AM","9/27/2012 2:31:13 AM","9/27/2012 2:33:59 AM","10/4/2012 9:54:35 AM","10/4/2012 10:16:07 AM","10/4/2012 10:27:48 AM","10/4/2012 10:55:51 AM","10/4/2012 11:03:34 AM","10/4/2012 11:07:00 PM","10/4/2012 11:34:14 AM","10/4/2012 11:37:10 AM","10/4/2012 11:40:25 AM","10/4/2012 11:58:51 AM","10/5/2012 4:53:58 AM","10/9/2012 11:59:05 PM","10/10/2012 12:07:39 AM","10/10/2012 12:47:47 AM","10/10/2012 12:52:10 AM","10/10/2012 1:06:16 AM","10/10/2012 1:33:23 AM","10/11/2012 7:15:48 AM","10/11/2012 7:28:16 AM","10/11/2012 7:37:54 AM","10/11/2012 7:39:42 AM","10/11/2012 7:53:02 AM","10/11/2012 7:59:39 AM","10/11/2012 8:02:25 AM","10/12/2012 6:11:30 AM","10/15/2012 7:50:32 AM","10/15/2012 7:56:01 AM","10/15/2012 7:59:24 AM","10/16/2012 6:50:34 AM","10/16/2012 6:51:38 AM","10/16/2012 6:57:06 AM","10/17/2012 1:24:17 AM","10/20/2012 1:27:11 AM"],"softwareagent":["Adobe InDesign 7.0","Adobe InDesign CS6 (Windows)"],"changed":["/;/metadata","/metadata","/"],"createdate":["10/20/2012 1:28:05 AM"],"modifydate":["10/26/2012 12:25:48 AM"],"metadatadate":["10/26/2012 12:25:48 AM"],"creatortool":["Adobe InDesign CS5 (7.0)"],"pagenumber":["1","2"],"format":["JPEG","application/pdf"],"width":["256"],"height":["256"],"image":["/9j/4AAQSkZJRgABAgEASABIAAD/7QAsUGhvdG9zaG9wIDMuMAA4QklNA+0AAAAAABAASAAAAAEA\nAQBIAAAAAQAB/+4AE0Fkb2JlAGSAAAAAAQUAAgAg/9sAhAAMCAgICAgMCAgMEAsLCxAUDg0NDhQY\nEhMTExIYFBIUFBQUEhQUGx4eHhsUJCcnJyckMjU1NTI7Ozs7Ozs7Ozs7AQ0LCxAOECIYGCIyKCEo\nMjsyMjIyOzs7Ozs7Ozs7Ozs7Ozs7OztAQEBAQDtAQEBAQEBAQEBAQEBAQEBAQEBAQED/wAARCAEA\nAKsDAREAAhEBAxEB/8QBQgAAAQUBAQEBAQEAAAAAAAAAAwABAgQFBgcICQoLAQABBQEBAQEBAQAA\nAAAAAAABAAIDBAUGBwgJCgsQAAEEAQMCBAIFBwYIBQMMMwEAAhEDBCESMQVBUWETInGBMgYUkaGx\nQiMkFVLBYjM0coLRQwclklPw4fFjczUWorKDJkSTVGRFwqN0NhfSVeJl8rOEw9N14/NGJ5SkhbSV\nxNTk9KW1xdXl9VZmdoaWprbG1ub2N0dXZ3eHl6e3x9fn9xEAAgIBAgQEAwQFBgcHBgI7AQACEQMh\nMRIEQVFhcSITBTKBkRShsUIjwVLR8DMkYuFygpJDUxVjczTxJQYWorKDByY1wtJEk1SjF2RFVTZ0\nZeLys4TD03Xj80aUpIW0lcTU5PSltcXV5fVWZnaGlqa2xtbm9ic3R1dnd4eXp7fH1+f3/9oADAMB\nAAIRAxEAPwD0/D/olH/Fs/6kJKTJKUkpSSlJKUkpSSlJKUkpSSlJKUkpSSlJKUkpSSlJKUkpSSlJ\nKUkpobj9sidPtcfL7LKSmzh/0Sj/AItn/UhJSZJSklKSUpJSklKSUpJSklKSUpJSklKSUpJSklKS\nUpJSklKSUpJSklOf/wBrf/Qz/wB1ElNrD/olH/Fs/wCpCSkySlJKUkpSSlJKUkpSSlJKUkpSSlJK\nUkpSSlJKUkpSSlJKUkpSSlJKc/8A7W/+hn/uokptYf8ARKP+LZ/1ISUmSUpJSklKSUpJSklKSUpJ\nSklKSUpJSklKSUpJSklKSUpJSklKSUpJTn/9rf8A0M/91ElNrD/olH/Fs/6kJKTJKUkpSSlJKUkp\nSSlJKRZV4xcW7JLS8U1usLW8nYC6B9ySnnP+fVP/AHAyfuCSlf8APqn/ALgZP3BJSv8An1T/ANwM\nn7gkp3OldSb1XDGY2p9Ic4t2WfS9qSm4kpSSlJKUkpSSlJKUkpSSnP8A+1v/AKGf+6iSm1h/0Sj/\nAItn/UhJSZJSklKSUpJSklKSUpJSklKSUpJSklKSUpJSklKSUpJSklKSUpJSklOf/wBrf/Qz/wB1\nElNrD/olH/Fs/wCpCSkySlJKUkpSSlJKUkpSSlJKUkpSSlJKUkpSSlJKUkpSSlJKUkpSSlJKc/8A\n7W/+hn/uokptYf8ARKP+LZ/1ISUmSUpJSklKSUpJSklKSUpJSklKSUpJSklKSUpJSklKSUpJSklK\nSUpJTn/9rf8A0M/91ElNrD/olH/Fs/6kJKTJKUkpSSlJKUkpSSlJKUkpSSlJKUkpSSlJKUkpSSlJ\nKUkpSSlJKUkpz/8Atb/6Gf8AuokptYf9Eo/4tn/UhJSZJSklKSUpJSklKSUpJSklKSUpJSklKSUp\nJSklKSUpJSklKSUpJSklOf8A9rf/AEM/91ElNrD/AKJR/wAWz/qQkpMkpSSlJKUkpSSlJKUkpSSl\nJKUkpSSlJKUkpSSlJKUkpSSlJKUkpSSnP/7W/wDoZ/7qJKbWH/RKP+LZ/wBSElJklKSUpJSklKSU\npJSklKSUpJSklKSUpJSklKSUpJSklKSUpJSklKSU5/8A2t/9DP8A3USU2sP+iUf8Wz/qQkpMkpSS\nlJKUkpSSlJKUkpSSlJKUkpSSlJKUkpSSlJKUkpSSlJKUkpSSnP8A+1v/AKGf+6iSm1h/0Sj/AItn\n/UhJSZJSklKSUpJSklPEfWGq/wCqP1gx/rfTdfZ0zKd9l6rTZY+1tQtdLLmB7ztaHngccDlJTsY2\nXj4RPW85rnZnWLG04dDRNhqaHOopbuDIJbusduMAuMmAElLu+ufSacHLzcyvJxj0+30Muh1Rssqc\nRuaX/ZzczaW6h27b5ykpyvrL9a7cjo4/ZWPmVi7NxsSywsFDn1Xljnei6yxjveHFjXjvqDEOSUro\nlHRK/rEejV4fUunZdXS3tbTdew1jFfdy2zHybXizfZo7dPzSU0+m29NH1D6jV167K+x25eXj231C\n2+5rG2ODS54baQA1kbn6dikp0OutY3qv1VyMey9rLr21Gt1r9jq21PsZvq3msun86J80lOz1X6xU\n9Gm7NxMoYTCBbnNax1VZJ2+5vq+tE/nCsjXlJTDqX1r6X0zMr6fazJuyLq3XVV0UWWb2saXnYQ2H\nHt7SedYSU6uPc3IoryGgtbaxrwHaOAcJg866pKSJKUkpSSlJKUkpz/8Atb/6Gf8AuokptYf9Eo/4\ntn/UhJSZJSklKSUpJSO7IoxwHX2MqB0Be4Nn70lPN/Xeg/WH6v39F6blYTX5Rr32ZF+wMbW9lvtD\nK7NxJZHZJTX650uvrvS+mjIv6c3N6baLvs9toyMW3aCz03ufWx0ObGuzTzSUx6n01mT9WczpHTKe\njdOuzxssZRf6dTR/pN9eM0vdoNNjfikpl12nqHVekdOw6bemV34uRTkX78x2z9WcHMbW4Y0nfGst\nG3+UkpQoz2/XB/1mFvTDU7p32EUnMcHb9wuDifsxEbxt+Hu/kpKaNfSuqN+qnUfq86/pXq51tz2W\njNfta3Ic+x8j7LMtMAeOvEapTb6hT1TLf0O2t/Sg7pD/AFrWuznw9wa+na0jEOm2HSRzpGklKQ9U\n6A7qeT1LHyOrMtweouDq3u6he12M0xvqbiNd6FjdPbuIjwKSm7l49/8Azk6b1PCu6e7D6dQ/Gi3L\nLbXNtDA521tD2y3boN2vkkp6arLxL3FlF1drgJLWPDjHjoUlJklKSUpJSklKSU5//a3/ANDP/dRJ\nTaw/6JR/xbP+pCSkySlJKUkpSSnN610PG65TXTk2PrFTi8GuJJIj84FJTkf+N90v/uRkfez/AMgk\npX/jfdL/AO5GR97P/IJKV/433S/+5GR97P8AyCSlf+N90v8A7kZH3s/8gkpX/jfdL/7kZH3s/wDI\nJKV/433S/wDuRkfez/yCSlf+N90v/uRkfez/AMgkpX/jfdL/AO5GR97P/IJKV/433S/+5GR97P8A\nyCSm/wBF+q2F0TKdl49ttjn1moizbEEtd+a0fupKdpJSklKSUpJSklOf/wBrf/Qz/wB1ElNrD/ol\nH/Fs/wCpCSkySlJKUkpSSlJKUkpSSlJKUkpSSlJKUkpSSlJKUkpSSlJKUkpSSlJKc/8A7W/+hn/u\nokptYf8ARKP+LZ/1ISUmSUpJSklKSUpJSklKSUpJSklKSUpJSklKSUpJSklKSUpJSklKSUpJTn/9\nrf8A0M/91ElNrD/olH/Fs/6kJKTJKUkpSSlJKUkpSSlJKUkpSSlJKUkpSSlJKUkpSSlJKUkpSSlJ\nKUkpz/8Atb/6Gf8AuokptYf9Eo/4tn/UhJSZJSklKSUpJSklKSUpJSklKSUpJSklKSUpJSklKSUp\nJSklKSUpJSklOf8A9rf/AEM/91ElNrD/AKJR/wAWz/qQkpMkpSSlJKUkpSSlJKUkpSSlJKUkpSSl\nJKUkpSSlJKUkpSSlJKUkpSSnP/7W/wDoZ/7qJKbWH/RKP+LZ/wBSElJklKSUpJSklKSUpJSklKSU\npJSklKSUpJSklKSUpJSklKSUpJSklKSU5/8A2t/9DP8A3USU2sP+iUf8Wz/qQkpMkpSSlJKUkpSS\nlJKUkpSSlJKUkpSSlJKUkpSSlJKUkpSSlJKUkpSSnP8A+1v/AKGf+6iSm1h/0Sj/AItn/UhJSZJS\nklKSUpJSklKSUpJSklKSUpJSklKSUpJSklKSUpJSklKSUpJSklOf/wBrf/Qz/wB1ElNrD/olH/Fs\n/wCpCSkySlJKUkpSSlJKUkpSSlJKed/599D/AOG/zB/5JJSv+ffQ/wDhv8wf+SSUr/n30P8A4b/M\nH/kklO5h5dWdi1ZdE+nc3c3cIMHxSUmSUpJSklKSUpJSklKSUpJTn/8Aa3/0M/8AdRJTaw/6JR/x\nbP8AqQkpMkpSSlJKUkpSSlJKQ5bshmJc/FaH3treamngvAO0HUd0lPM/tD6+f9wKfw/9LJKa8fWz\n/wApsP8A7br/APSqSlR9bP8Aymw/+26//SqSlR9bP/KbD/7br/8ASqSk7M3681sDK+nUMa3QNaGg\nD4AXJKeg6Pb1K7Ca/q1bacnc4FjeInThzvypKbqSlJKUkpSSlJKUkpSSnP8A+1v/AKGf+6iSm1h/\n0Sj/AItn/UhJSZJSklKSUpJSklKSUpJSklOTkfWnoWJe/GyMrZbU4te307DBHmGEJKR/88fq5/3L\n/wDArf8A0mkpX/PH6uf9y/8AwK3/ANJpKdkEOAcODqElLpKUkpSSlJKUkpSSlJKUkpz/APtb/wCh\nn/uokptYf9Eo/wCLZ/1ISUmSUpJSklKSUpJSklKSUpJTSt6L0i+x112HS+x53Oc5jSST3JhJTD9g\ndE/7g4//AG23+5JSv2B0T/uDj/8Abbf7klN8AAQNAElLpKUkpSSlJKUkpSSlJKUkpz/+1v8A6Gf+\n6iSm1h/0Sj/i2f8AUhJSZJSklKSUpJSklKSUpJSklKSUpJSklKSUpJSklKSUpJSklKSUpJSklOf/\nANrf/Qz/AN1ElNrD/olH/Fs/6kJKTJKUkpSSlJKUkpSSlJKUkpSSlJKUkpSSlJKUkpSSlJKUkpSS\nlJKUkpz/APtb/wChn/uokptYf9Eo/wCLZ/1ISUmSUpJSklKSUpJSklKSUpJSklKSUpJSklKSUpJS\nklKSUpJSklKSUpJTn/8Aa3/0M/8AdRJSTDzMQYlAN9f82z89v7o80lJvtmJ/p6/89v8AekpX2zE/\n09f+e3+9JSvtmJ/p6/8APb/ekpX2zE/09f8Ant/vSUr7Zif6ev8Az2/3pKV9sxP9PX/nt/vSUr7Z\nif6ev/Pb/ekpX2zE/wBPX/nt/vSUr7Zif6ev/Pb/AHpKV9sxP9PX/nt/vSUr7Zif6ev/AD2/3pKV\n9sxP9PX/AJ7f70lK+2Yn+nr/AM9v96SlfbMT/T1/57f70lK+2Yn+nr/z2/3pKV9sxP8AT1/57f70\nlK+2Yn+nr/z2/wB6SlfbMT/T1/57f70lK+2Yn+nr/wA9v96SlfbMT/T1/wCe3+9JTQ+1Yv2yfWrj\n7XM7hx9ljxSU/wD/2Q==","/9j/4AAQSkZJRgABAgEASABIAAD/7QAsUGhvdG9zaG9wIDMuMAA4QklNA+0AAAAAABAASAAAAAEA\nAQBIAAAAAQAB/+4AE0Fkb2JlAGSAAAAAAQUAAgAg/9sAhAAMCAgICAgMCAgMEAsLCxAUDg0NDhQY\nEhMTExIYFBIUFBQUEhQUGx4eHhsUJCcnJyckMjU1NTI7Ozs7Ozs7Ozs7AQ0LCxAOECIYGCIyKCEo\nMjsyMjIyOzs7Ozs7Ozs7Ozs7Ozs7OztAQEBAQDtAQEBAQEBAQEBAQEBAQEBAQEBAQED/wAARCAEA\nAKsDAREAAhEBAxEB/8QBQgAAAQUBAQEBAQEAAAAAAAAAAwABAgQFBgcICQoLAQABBQEBAQEBAQAA\nAAAAAAABAAIDBAUGBwgJCgsQAAEEAQMCBAIFBwYIBQMMMwEAAhEDBCESMQVBUWETInGBMgYUkaGx\nQiMkFVLBYjM0coLRQwclklPw4fFjczUWorKDJkSTVGRFwqN0NhfSVeJl8rOEw9N14/NGJ5SkhbSV\nxNTk9KW1xdXl9VZmdoaWprbG1ub2N0dXZ3eHl6e3x9fn9xEAAgIBAgQEAwQFBgcHBgI7AQACEQMh\nMRIEQVFhcSITBTKBkRShsUIjwVLR8DMkYuFygpJDUxVjczTxJQYWorKDByY1wtJEk1SjF2RFVTZ0\nZeLys4TD03Xj80aUpIW0lcTU5PSltcXV5fVWZnaGlqa2xtbm9ic3R1dnd4eXp7fH1+f3/9oADAMB\nAAIRAxEAPwD1VJSklKSUpJSklKSUpJSklKSUpJSklKSUpJSklKSUpJSklKSUpJSklKSU5c/5Q/8A\nQ7/3SSU6iSlJKUkpSSlJKUkpSSlJKUkpSSlJKUkpSSlJKUkpSSlJKUkpSSlJKUkpy/8AvQ/9D/8A\n3SSU6iSlJKUkpSSlJKUkpSSlJKUkpSSlJKUkpSSlJKUkpSSlJKUkpSSlJKUkpy/+9D/0P/8AdJJT\nqJKUkpSSmvRRdVk5NtlpfXc5jqmEmKw1jWkCfEiUlNhJSklKSUpJSklKSUpJSklKSUpJSklKSUpJ\nSklKSUpJSklOX/3of+h//ukkp1ElKSUpJSklKSUpJSklKSUpJSklKSUpJSklKSUpJSklKSUpJSkl\nKSUpJTl/96H/AKH/APukkp1ElKSUpJSklKSUpJSklKSUpJSklKSUpJSklKSUpJSklKSUpJSklKSU\npJTl/wDeh/6H/wDukkp1ElKSUpJSklKSUpJSklKSUpJSklKSUpJSklKSUpJSklKSUpJSklKSUpJT\nl/8Aeh/6H/8Aukkp1ElKSUpJSzp2nbzBj4pKeT9X69/v4/31JKV6v17/AH8f76klK9X69nQPx/vq\nSUy/9eB/wP8A4GkpX/rwP+B/8DSUr/14H/A/+BpKV/68D/gf/A0lK/8AXgf8D/4GkpX/AK8D/gf/\nAANJSv8A14H/AAP/AIGkpX/rwP8Agf8AwNJSv/Xgf8D/AOBpKZ0/8+/Wr9b0fT3DfHpztnX8ElPU\nJKUkpSSlJKcv/vQ/9D//AHSSU6iSlJKUkpZzdzS09xH3pKeX/wDG+6X/ANyMj72f+QSUr/xvul/9\nyMj72f8AkElJMf6idNxsirJZfeXUvbYAS2CWkO19nkkp6VJSklKSUpJSklKSUpJSklKSUpJSklKS\nUpJSklOX/wB6H/of/wC6SSnUSUpJSklKSUpJSklKSUpJSklKSUpJSklKSUpJSklKSUpJSklKSUpJ\nSklOX/3of+h//ukkp1ElKSUpJTGyNjpMCDr4JKfPPS6V/wDPJd/7D3/+TSUr0ulf/PJd/wCw9/8A\n5NJSvS6V/wDPJd/7D3/+TSUr0ulf/PJd/wCw9/8A5NJSvS6V/wDPJd/7D3/+TSUr0ulf/PJd/wCw\n9/8A5NJSvS6V/wDPJd/7D3/+TSUr0ulf/PJd/wCw9/8A5NJSvS6V/wDPJd/7D3/+TSUr0ulf/PJd\n/wCw9/8A5NJSvS6V/wDPJd/7D3/+TSUr0ulf/PJd/wCw9/8A5NJSvS6V/wDPJd/7D3/+TSUnwbOk\nYeZTlP8ArBbc2p4eazReA6O30nfkSU9zjZNOZQzJx3b6rRuY6CJB8nAFJSVJSklOX/3of+h//ukk\np1ElKSUpJSxAIIPB0KSnO/5t9C/7g0/5qSlf82+hf9waf81JSv8Am30L/uDT/mpKV/zb6F/3Bp/z\nUlK/5t9C/wC4NP8AmpKV/wA2+hf9waf81JSv+bfQv+4NP+akpX/NvoX/AHBp/wA1JSv+bfQv+4NP\n+akpX/NvoX/cGn/NSUr/AJt9C/7g0/5qSlf82+hf9waf81JSv+bfQv8AuDT/AJqSlf8ANvoX/cGn\n/NSU3qaasaptFDQytghrRwAkpIkpSSnL/wC9D/0P/wDdJJTqJKUkpSSlJKUkpSSlJKUkpSSlJKUk\npSSlJKUkpSSlJKUkpSSlJKUkpSSnL/70P/Q//wB0klOokpSSlJKUkpSSlJKUkpSSlJKUkpSSlJKU\nkpSSlJKUkpSSlJKUkpSSlJKcv/vQ/wDQ/wD90klOokpSSlJKUkpSSlJKUkpSSlJKUkpSSlJKUkpS\nSlJKUkpSSlJKUkpSSlJKcv8A70P/AEP/APdJJTqJKUkpSSlJKUkpSSlJKUkpSSlJKUkpSSlJKUkp\nSSlJKUkpSSlJKUkpSSnL/wC9D/0P/wDdJJTqJKUkpSSlJKUkpSSlJKUkpSSlJKUkpSSlJKUkpSSl\nJKUkpSSlJKUkpSSnL/70P/Q//wB0klOokpSSlJKUkpSSlJKUkpSSlJKUkpSSlJKUkpSSlJKUkpSS\nlJKUkpSSlJKcv/vQ/wDQ/wD90klOokpSSlJKWcSGkt1IBgeaSnlP2x9eP/Kyn/Nd/wClklK/bH14\n/wDKyn/Nd/6WSUr9sfXj/wArKf8ANd/6WSUr9sfXj/ysp/zXf+lklK/bH14/8rKf813/AKWSUr9s\nfXj/AMrKf813/pZJSv2x9eP/ACsp/wA13/pZJSv2x9eP/Kyn/Nd/6WSUr9sfXj/ysp/zXf8ApZJS\nv2x9eP8Aysp/zXf+lklK/bH14/8AKyn/ADXf+lklK/bH14/8rKf813/pZJSv2x9eP/Kyn/Nd/wCl\nklK/bH14/wDKyn/Nd/6WSUzo6v8AXR11bbum1NrLgHuDXaNJ1P8APFJT1KSlJKcv/vQ/9D//AHSS\nU6iSlJKUkp4v6w19Pd1jIN/W7MJ/snHbTa8M9jPzmOA15SU53pdK/wDnku/9h7//ACaSlel0r/55\nLv8A2Hv/APJpKV6XSv8A55Lv/Ye//wAmkpXpdK/+eS7/ANh7/wDyaSlel0r/AOeS7/2Hv/8AJpKV\n6XSv/nku/wDYe/8A8mkpXpdK/wDnku/9h7//ACaSlel0r/55Lv8A2Hv/APJpKV6XSv8A55Lv/Ye/\n/wAmkpXpdK/+eS7/ANh7/wDyaSlel0r/AOeS7/2Hv/8AJpKV6XSv/nku/wDYe/8A8mkpXpdK/wDn\nku/9h7//ACaSlel0r/55Lv8A2Hv/APJpKS4tXTPtVO36xW2H1Gww0XDcZHtkv7pKfQElKSU5f/eh\n/wCh/wD7pJKdRJSklKSU8h159o6reG9B+3D2frPp2O3+xvdrSNOElND1bv8A51v/AAK3/wAgkpXq\n3f8Azrf+BW/+QSUr1bv/AJ1v/Arf/IJKV6t3/wA63/gVv/kElK9W7/51v/Arf/IJKV6t3/zrf+BW\n/wDkElK9W7/51v8AwK3/AMgkpXq3f/Ot/wCBW/8AkElK9W7/AOdb/wACt/8AIJKV6t3/AM63/gVv\n/kElK9W7/wCdb/wK3/yCSlerd/8AOt/4Fb/5BJSvVu/+db/wK3/yCSlerd/863/gVv8A5BJSTGsu\nOTUD9WfS97f0np2jbqPd9Dskp7pJSklOX/3of+h//ukkp1ElKSUpJTz3Veg9bzc+3JxOqWY1L9u2\nlrrAGw1rTo1wGpEpKan/ADW+sf8A5d3f59v/AJNJSv8Amt9Y/wDy7u/z7f8AyaSlf81vrH/5d3f5\n9v8A5NJSv+a31j/8u7v8+3/yaSlf81vrH/5d3f59v/k0lK/5rfWP/wAu7v8APt/8mkpX/Nb6x/8A\nl3d/n2/+TSUr/mt9Y/8Ay7u/z7f/ACaSlf8ANb6x/wDl3d/n2/8Ak0lK/wCa31j/APLu7/Pt/wDJ\npKV/zW+sf/l3d/n2/wDk0lM6Pqz9Ya7q7H9Zte1jg5zS+3UAyR9NJT1KSlJKUkpSSlJKcv8A70P/\nAEP/APdJJTqJKUkpSSlJKUkpSSlJKUkpSSlJKUkpSSlJKUkpSSlJKUkpSSlJKUkpSSnL/wC9D/0P\n/wDdJJTqJKUkpSSlJKUkpSSlJKUkpSSlJKUkpSSlJKUkpSSlJKUkpSSlJKUkpSSnL/70P/Q//wB0\nklOokpSSlJKUkpSSlJKUkpSSlJKUkpSSlJKUkpSSlJKUkpSSlJKUkpSSlJKcv/vQ/wDQ/wD90klO\nokpSSlJKUkpSSlJKUkpSSlJKUkpSSlJKUkpSSlJKUkpSSlJKUkpSSlJKcv8A70P/AEP/APdJJTqJ\nKUkpSSlJKUkpSSlJKUkpSSlJKUkpSSlJKaXVOrYfR6W35rnNY92xpaC7WCe3wSU5v/PfoH+ks/7b\nKSlf89+gf6Sz/tspKV/z36B/pLP+2ykpX/PfoH+ks/7bKSmVX1z6FdYypllhc9wa32HkmAkp3UlK\nSU5f/eh/6H/+6SSnUSUpJSklKSUpJSklKSUpJSklKSUpJSklKSU8917J6+3L9DB6dTm4waHB1zN/\nuMz/AIRv5ElOZ6/1n/8AKLD/AO2f/UqSlev9Z/8Ayiw/+2f/AFKkpXr/AFn/APKLD/7Z/wDUqSle\nv9Z//KLD/wC2f/UqSmePd9ZDfWLOiYjGb27nCmC0TqR+lSU9ikpSSnL/AO9D/wBD/wD3SSU6iSlJ\nKUkpSSlJKUkpSSlJKUkpSSlJKUkpSSlJKUkpSSlJKUkpSSlJKUkpy/8AvQ/9D/8A3SSU6iSlJKUk\npSSlJKUkpSSlJKUkpSSlJKUkpSSlJKUkpSSlJKUkpSSlJKUkpy/+9D/0P/8AdJJTqJKUkpSSlJKU\nkpSSlJKUkpSSlJKUkpSSlJKUkpSSlJKUkpSSlJKUkpSSnL/70P8A0P8A/dJJTe+2Yn+nr/z2/wB6\nSlfbMT/T1/57f70lK+2Yn+nr/wA9v96SlfbMT/T1/wCe3+9JSvtmJ/p6/wDPb/ekpX2zE/09f+e3\n+9JSvtmJ/p6/89v96SlfbMT/AE9f+e3+9JSvtmJ/p6/89v8AekpX2zE/09f+e3+9JSvtmJ/p6/8A\nPb/ekpX2zE/09f8Ant/vSUr7Zif6ev8Az2/3pKV9sxP9PX/nt/vSUr7Zif6ev/Pb/ekpX2zE/wBP\nX/nt/vSUr7Zif6ev/Pb/AHpKV9sxP9PX/nt/vSUr7Zif6ev/AD2/3pKV9sxP9PX/AJ7f70lK+2Yn\n+nr/AM9v96SnM+1Yv2+fWrj7dM7hx9jjxSU//9k="],"docchangecount":["2030"],"keystampmp":["AAAAAA=="],"producer":["Adobe PDF Library 9.9"],"trapped":["False"]},"tampered":false,"appendable":false,"cryptomode":-1},"sha256":"27496F051F1CCCE22469E00C42B5E016C895DF9243F5184874642621959F918A","clean.language":"tr","clean.pageCount":"144","clean.creator":"adobe indesign cs5 (7.0)"}