{"file":{"path":"E:\\Downloads\\Yandex\\Kütüphane 8\\Carl Gustav Jung Doğu Metinlerine Psikolojik Yaklaşım İnsan Yayınları.pdf","name":"Carl Gustav Jung Doğu Metinlerine Psikolojik Yaklaşım İnsan Yayınları.pdf","ext":".pdf","length":8988168,"dir":"E:\\Downloads\\Yandex\\Kütüphane 8","creation":"2021-12-15T22:34:27","lastaccess":"2022-01-04T01:47:00","lastwrite":"2021-12-15T22:34:39"},"hash":{"md5":"0BF75548081FE54C10E0B0DCD2D5A623","sha1":"F6A43878CF98F9EAEA4BFC9F7FBC17EAE4EF0F23"},"tika":{"content-type":"application/pdf","creation-date":"2017-04-14T11:31:50","last-modified":"2018-04-23T16:37:48Z","last-save-date":"2018-04-23T16:37:48Z","x-parsed-by":["org.apache.tika.parser.DefaultParser","org.apache.tika.parser.pdf.PDFParser"],"access_permission.assemble_document":true,"access_permission.can_modify":true,"access_permission.can_print":true,"access_permission.can_print_degraded":true,"access_permission.extract_content":true,"access_permission.extract_for_accessibility":true,"access_permission.fill_in_form":true,"access_permission.modify_annotations":true,"created":"2017-04-14T11:31:50","date":"2018-04-23T16:37:48Z","dc.format":"application/pdf; version=1.5","dcterms.created":"2017-04-14T11:31:50Z","dcterms.modified":"2018-04-23T16:37:48Z","meta.creation-date":"2017-04-14T11:31:50Z","meta.save-date":"2018-04-23T16:37:48Z","modified":"2018-04-23T16:37:48Z","pdf.pdfversion":"1.5","pdf.charsperpage":["0","439","0","539","842","0","1180","2544","2313","2555","2542","2389","2604","2513","2612","2576","2553","2299","2592","2587","2558","2592","2597","2612","2521","2638","2309","2585","2442","2542","2465","2546","2466","2590","2575","2452","2448","2624","1976","1207","557","360","1217","2486","2413","2489","2500","2472","2607","2546","2360","109","1229","2591","2466","2585","2541","2551","2566","2494","2229","1173","1258","2540","2641","2549","2616","2547","2333","2646","2640","1670","1164","2502","2562","2563","2388","2400","1489","1261","2581","2534","2567","2290","2561","406","1270","1786","1475","1649","2311","1779","1575","792","1396","1435","2019","2417","1424","1348","2540","2622","2569","2404","2542","2630","2560","2530","2596","2563","2174","2232","2558","2574","2699","2559","2315","2349","290","0","230","0","2540","2612","2568","2603","2409","2609","2682","2509","2208","2443","2516","2529","2270","2524","2490","2587","2552","2279","925","2111","2878","960","2516","2265","2548","2594","2560","2401","1809","2555","1986","2002","2564","2506","2624","2263","2088","2230","2457","1299","2628","1246","2437","1919","2344","2109","1893","1719","1793","2593","1879","2334","2357","2106","1948","1189","2291","2537","2480","2624","2503","2655","2594","2552","457","1200","2579","2562","2516","2632","2528","2554","2534","359","1197","2503","2543","2080","2518","2465","2163","2454","2554","2582","2538","2505","2646","2631","2379","2024","0","1206","2590","2349","2338","2637","2601","2567","2646","2604","2593","2386","2282","2510","2682","2543","1143","1136","2464","2619","2479","2617","2615","2542","2612","2559","2635","2589","2599","2674","2642","2629","2507","1478","2042","1154","2487","2591","2483","2404","2668","2676","2463","2521","2631","2653","2594","2516","2584","2634","2588","455","2013","2203","2413","1260","2442","2279","2577","115","2571","1403","1232","2541","2132","599","1135","1831","781","1839","1478","806","1383","1444","1402","1416","636"],"pdf.docinfo.created":"2017-04-14T11:31:50Z","pdf.docinfo.creator_tool":"Microsoft® Word 2013","pdf.docinfo.modified":"2018-04-23T16:37:48Z","pdf.docinfo.producer":"ABBYY FineReader 12","pdf.encrypted":false,"pdf.hasmarkedcontent":true,"pdf.hasxfa":false,"pdf.hasxmp":true,"pdf.producer":"ABBYY FineReader 12","pdf.unmappedunicodecharsperpage":["0","0","0","0","0","0","0","0","0","0","0","0","0","0","0","0","0","0","0","0","0","0","0","0","0","0","0","0","0","0","0","0","0","0","0","0","0","0","0","0","0","0","0","0","0","0","0","0","0","0","0","0","0","0","0","0","0","0","0","0","0","0","0","0","0","0","0","0","0","0","0","0","0","0","0","0","0","0","0","0","0","0","0","0","0","0","0","0","0","0","0","0","0","0","0","0","0","0","0","0","0","0","0","0","0","0","0","0","0","0","0","0","0","0","0","0","0","0","0","0","0","0","0","0","0","0","0","0","0","0","0","0","0","0","0","0","0","0","0","0","0","0","0","0","0","0","0","0","0","0","0","0","0","0","0","0","0","0","0","0","0","0","0","0","0","0","0","0","0","0","0","0","0","0","0","0","0","0","0","0","0","0","0","0","0","0","0","0","0","0","0","0","0","0","0","0","0","0","0","0","0","0","0","0","0","0","0","0","0","0","0","0","0","0","0","0","0","0","0","0","0","0","0","0","0","0","0","0","0","0","0","0","0","0","0","0","0","0","0","0","0","0","0","0","0","0","0","0","0","0","0","0","0","0","0","0","0","0","0","0","0","0","0","0","0","0","0","0","0","0","0","0","0","0","0","0","0","0","0","0","0","0","0","0","0","0","0","0","0"],"producer":"ABBYY FineReader 12","xmp.createdate":"2017-04-14T11:31:50Z","xmp.creatortool":"Microsoft® Word 2013","xmp.metadatadate":"2018-04-23T19:37:48Z","xmp.modifydate":"2018-04-23T19:37:48Z","xmpmm.documentid":"uuid:3bbef357-a7f4-42fc-ab8d-b1f8f0267b84"},"pdf":{"info":{"creationdate_error":"D:20170414113150Z","moddate":"D:20180423193748+03'00'","producer":"ABBYY FineReader 12"},"pdfversion":"5","metadata":{"x__x":["Adobe XMP Core 5.4-c005 78.147326, 2012/08/23-13:03:03        "],"format":["application/pdf"],"seq":["ergin yilmaz"],"createdate":["4/14/2017 11:31:50 AM"],"creatortool":["Microsoft® Word 2013"],"modifydate":["4/23/2018 8:37:48 PM"],"metadatadate":["4/23/2018 8:37:48 PM"],"producer":["ABBYY FineReader 12"],"documentid":["uuid:3bbef357-a7f4-42fc-ab8d-b1f8f0267b84"],"instanceid":["uuid:d0f727a0-9f83-443d-aef2-681d6f728de2"]},"tampered":false,"appendable":false,"cryptomode":-1},"sha256":"33BDCDF661C4BA610873E8B58AECC19CB7A77689CDC79EC91C5954DAD161640A","clean.language":"tr","clean.pageCount":"289","clean.author":"ergin yilmaz","clean.creator":"[\"ergin yilmaz\",\"microsoft® word 2013\"]"}