{"file":{"path":"D:\\GOOGLE.PHOTO\\gm.upload\\1001 Temel Eser-20220103T120944Z-001\\1001 Temel Eser\\Cem Sultan _ Cem Sultan_ın Türkçe Divanı 2.pdf","name":"Cem Sultan _ Cem Sultan_ın Türkçe Divanı 2.pdf","ext":".pdf","length":3893929,"dir":"D:\\GOOGLE.PHOTO\\gm.upload\\1001 Temel Eser-20220103T120944Z-001\\1001 Temel Eser","creation":"2022-01-03T18:00:22","lastaccess":"2022-01-03T23:29:38","lastwrite":"2017-02-20T11:31:36"},"hash":{"md5":"53F903DF85A73180F134ACEDD5037519","sha1":"38C0E57CA7123083A53D36999216A53E33D98F11"},"tika":{"content-type":"application/pdf","creation-date":"2012-08-05T11:44:12","last-modified":"2012-08-05T16:05:02Z","last-save-date":"2012-08-05T16:05:02Z","x-parsed-by":["org.apache.tika.parser.DefaultParser","org.apache.tika.parser.pdf.PDFParser"],"access_permission.assemble_document":false,"access_permission.can_modify":false,"access_permission.can_print":false,"access_permission.can_print_degraded":false,"access_permission.extract_content":false,"access_permission.extract_for_accessibility":true,"access_permission.fill_in_form":false,"access_permission.modify_annotations":false,"created":"2012-08-05T11:44:12","date":"2012-08-05T16:05:02Z","dc.format":["application/pdf; version=1.7","application/pdf; version=\"1.7 Adobe Extension Level 3\""],"dcterms.created":"2012-08-05T11:44:12Z","dcterms.modified":"2012-08-05T16:05:02Z","meta.creation-date":"2012-08-05T11:44:12Z","meta.save-date":"2012-08-05T16:05:02Z","modified":"2012-08-05T16:05:02Z","pdf.pdfextensionversion":"1.7 Adobe Extension Level 3","pdf.pdfversion":"1.7","pdf.charsperpage":["32","0","0","0","0","0","0","0","0","0","0","0","0","0","0","0","0","0","0","0","0","0","0","0","0","0","0","0","0","0","0","0","0","0","0","0","0","0","0","0","0","0","0","0","0","0","0","0","0","0","0","0","0","0","0","0","0","0","0","0","0","0","0","0","0","0","0","0","0","0","0","0","0","0","0","0","0","0","0","0","0","0","0","0","0","0","0","0","0","0","0","0","0","0","0","0","0","0","0","0","0","0","0","0","0","0","0","0","0","0","0","0","0","0","0","0","0","0","0","0","0","0","0","0","0","0","0","0","0","0","0","0","0","0","0","0","0","0","0","0","0","0","0","0","0","0","0","0","0","0","0","0","0","0","0","0","0","0","0","0","0","0","0","0","0","0","0","0","0","0","0","0","0","0","0","0","0","0","0","0","0","0","0","0","0","0","0","0","0","0","0","0","0"],"pdf.docinfo.created":"2012-08-05T11:44:12Z","pdf.docinfo.creator_tool":"Adobe Acrobat 9.0","pdf.docinfo.modified":"2012-08-05T16:05:02Z","pdf.docinfo.producer":"Adobe Acrobat 9.0 Image Conversion Plug-in","pdf.encrypted":true,"pdf.hasmarkedcontent":true,"pdf.hasxfa":false,"pdf.hasxmp":true,"pdf.producer":"Adobe Acrobat 9.0 Image Conversion Plug-in","pdf.unmappedunicodecharsperpage":["0","0","0","0","0","0","0","0","0","0","0","0","0","0","0","0","0","0","0","0","0","0","0","0","0","0","0","0","0","0","0","0","0","0","0","0","0","0","0","0","0","0","0","0","0","0","0","0","0","0","0","0","0","0","0","0","0","0","0","0","0","0","0","0","0","0","0","0","0","0","0","0","0","0","0","0","0","0","0","0","0","0","0","0","0","0","0","0","0","0","0","0","0","0","0","0","0","0","0","0","0","0","0","0","0","0","0","0","0","0","0","0","0","0","0","0","0","0","0","0","0","0","0","0","0","0","0","0","0","0","0","0","0","0","0","0","0","0","0","0","0","0","0","0","0","0","0","0","0","0","0","0","0","0","0","0","0","0","0","0","0","0","0","0","0","0","0","0","0","0","0","0","0","0","0","0","0","0","0","0","0","0","0","0","0","0","0","0","0","0","0","0","0"],"producer":"Adobe Acrobat 9.0 Image Conversion Plug-in","xmp.createdate":"2012-08-05T14:44:12Z","xmp.creatortool":"Adobe Acrobat 9.0","xmp.metadatadate":"2012-08-05T19:05:02Z","xmp.modifydate":"2012-08-05T19:05:02Z","xmpmm.documentid":"uuid:af3cf089-e3ac-4545-b210-8f4e04816280"},"pdf":{"info":{"creationdate_error":"D:20120805144412+03'00'","moddate":"D:20120805190502+03'00'","producer":"Adobe Acrobat 9.0 Image Conversion Plug-in"},"pdfversion":"7","metadata":{"x__x":["Adobe XMP Core 4.2.1-c041 52.342996, 2008/05/07-20:48:00        "],"modifydate":["8/5/2012 9:05:02 PM"],"createdate":["8/5/2012 4:44:12 PM"],"metadatadate":["8/5/2012 9:05:02 PM"],"creatortool":["Adobe Acrobat 9.0"],"format":["application/pdf"],"documentid":["uuid:af3cf089-e3ac-4545-b210-8f4e04816280"],"instanceid":["uuid:a3d0472e-e74a-4724-b021-5e93b22afad2"],"producer":["Adobe Acrobat 9.0 Image Conversion Plug-in"]},"tampered":false,"appendable":false,"cryptomode":3},"sha256":"3565756DA47DEC2CC8340B19EF67BBF1CD0934E76716E4D735E7F99A54EA7CDE","clean.language":"br","clean.pageCount":"193","clean.creator":"adobe acrobat 9.0"}