{"file":{"path":"D:\\SHARED\\Tamamdir\\___AZ_CORPUS\\49ee457506b8dfb999983042aa9c9e59.pdf","name":"49ee457506b8dfb999983042aa9c9e59.pdf","ext":".pdf","length":560677,"dir":"D:\\SHARED\\Tamamdir\\___AZ_CORPUS","creation":"2015-07-07T22:51:57","lastaccess":"2020-12-17T01:16:31","lastwrite":"2015-07-07T22:51:57"},"hash":{"md5":"49EE457506B8DFB999983042AA9C9E59","sha1":"023F9C4B86D02D12424F242A2DECF441CB799FF0"},"tika":{"content-type":"application/pdf","creation-date":"2015-07-07T09:10:44","last-modified":"2015-07-07T09:10:44","last-save-date":"2015-07-07T09:10:44","x-parsed-by":["org.apache.tika.parser.DefaultParser","org.apache.tika.parser.pdf.PDFParser"],"access_permission.assemble_document":"true","access_permission.can_modify":"true","access_permission.can_print":"true","access_permission.can_print_degraded":"true","access_permission.extract_content":"true","access_permission.extract_for_accessibility":"true","access_permission.fill_in_form":"true","access_permission.modify_annotations":"true","created":"2015-07-07T09:10:44","date":"2015-07-07T09:10:44","dc.format":"application/pdf; version=1.4","dcterms.created":"2015-07-07T09:10:44","dcterms.modified":"2015-07-07T09:10:44","meta.creation-date":"2015-07-07T09:10:44","meta.save-date":"2015-07-07T09:10:44","modified":"2015-07-07T09:10:44","pdf.pdfversion":"2020-01-04T00:00:00","pdf.charsperpage":["482","200","1836","1988","2032","1944","1991","1904","1976","1802","1962","1642","2116","1680","1868","1802","1628","2024","1516","1677","1426","1602","1680","1478","1652","1509","825","825","935","1220","932","914","814","785","955","714","890","828","1003","833","1121","1148","866","768","931","1204","764","1079","1256","987","872","671","1117","1113","1145","1280","1310","1207","1311","987","1320","1209","1307","1036","1097","1167","1279","909","1062","758","949","922","1166","907","1360","1352","1460","1430","1222","834","1259","1042","834","937","936","913","937","894","1009","968","916","963","1098","927","1114","985","1377","1210","1117","1285","1188","1161","967","1276","1121","1189","1206","1084","820","977","1354","865","5"],"pdf.docinfo.created":"2015-07-07T09:10:44","pdf.docinfo.creator_tool":"PScript5.dll Version 5.2.2","pdf.docinfo.modified":"2015-07-07T09:10:44","pdf.docinfo.producer":"GPL Ghostscript 9.06","pdf.encrypted":"false","pdf.hasmarkedcontent":"false","pdf.hasxfa":"false","pdf.hasxmp":"true","pdf.producer":"GPL Ghostscript 9.06","pdf.unmappedunicodecharsperpage":["0","0","0","0","0","0","0","0","0","0","0","0","0","0","0","0","0","0","0","0","0","0","0","0","0","0","0","0","0","0","0","0","0","0","0","0","0","0","0","0","0","0","0","0","0","0","0","0","0","0","0","0","0","0","0","0","0","0","0","0","0","0","0","0","0","0","0","0","0","0","0","0","0","0","0","0","0","0","0","0","0","0","0","0","0","0","0","0","0","0","0","0","0","0","0","0","0","0","0","0","0","0","0","0","0","0","0","0","0","0","0","0","0"],"producer":"GPL Ghostscript 9.06","xmp.about":"uuid:8be6046a-26e3-11e5-0000-feb7bccfe95c","xmp.createdate":"2015-07-07T14:10:44","xmp.creatortool":"PScript5.dll Version 5.2.2","xmp.modifydate":"2015-07-07T14:10:44","xmpmm.documentid":"uuid:8be6046a-26e3-11e5-0000-feb7bccfe95c"},"pdf":{"info":{"producer":"GPL Ghostscript 9.06","creationdate":"D:20150707141044+05'00'","moddate":"D:20150707141044+05'00'"},"pdfversion":"4","metadata":{"about":["uuid:8be6046a-26e3-11e5-0000-feb7bccfe95c"],"producer":["GPL Ghostscript 9.06"],"modifydate":["7/7/2015 2:10:44 AM"],"createdate":["7/7/2015 2:10:44 AM"],"creatortool":["PScript5.dll Version 5.2.2"],"documentid":["uuid:8be6046a-26e3-11e5-0000-feb7bccfe95c"],"format":["application/pdf"],"text":["Microsoft Word - TEST"],"seq":["Telebe"]},"tampered":false,"appendable":false,"cryptomode":-1},"sha256":"59BECE6F2D9C30BB0FF25E78CC6E4C49E248F285732FAEA67591D42473BD021D","clean.language":"tr","clean.title":"microsoft word - test","clean.pageCount":"113","clean.author":"telebe","clean.creator":"[\"telebe\",\"pscript5.dll version 5.2.2\"]"}