{"file":{"path":"E:\\Downloads\\Yandex\\E-KİTAP- (2)\\DERGİLER\\2005.LEVEL SAYILARI\\2005\\2005-105-52.pdf","name":"2005-105-52.pdf","ext":".pdf","length":221999,"dir":"E:\\Downloads\\Yandex\\E-KİTAP- (2)\\DERGİLER\\2005.LEVEL SAYILARI\\2005","creation":"2022-01-04T16:01:13","lastaccess":"2022-01-04T23:49:53","lastwrite":"2007-07-10T23:58:08"},"hash":{"md5":"885C066778863EEF9D3A89CC757416F8","sha1":"664ADC8276FE8C0FC01EB987BE55D7A6EA2F1C75"},"tika":{"content-type":"application/pdf","creation-date":"2007-07-10T14:59:30","last-modified":"2007-07-10T19:58:04Z","last-save-date":"2007-07-10T19:58:04Z","x-parsed-by":["org.apache.tika.parser.DefaultParser","org.apache.tika.parser.pdf.PDFParser"],"xpressprivate":"%%DocumentProcessColors: Cyan Magenta Yellow Black\n%%DocumentCustomColors: (Red)\n%%+ (Blue)\n%%CMYKCustomColor: 0 .996 .988 0 (Red)\n%%+ .996 .957 0 0 (Blue)\n%%EndComments","access_permission.assemble_document":true,"access_permission.can_modify":true,"access_permission.can_print":true,"access_permission.can_print_degraded":true,"access_permission.extract_content":true,"access_permission.extract_for_accessibility":true,"access_permission.fill_in_form":true,"access_permission.modify_annotations":true,"created":"2007-07-10T14:59:30","date":"2007-07-10T19:58:04Z","dc.format":"application/pdf; version=1.4","dcterms.created":"2007-07-10T14:59:30Z","dcterms.modified":"2007-07-10T19:58:04Z","meta.creation-date":"2007-07-10T14:59:30Z","meta.save-date":"2007-07-10T19:58:04Z","modified":"2007-07-10T19:58:04Z","pdf.pdfversion":"1.4","pdf.charsperpage":["2462","5886"],"pdf.docinfo.created":"2007-07-10T14:59:30Z","pdf.docinfo.creator_tool":"QuarkXPress(tm) 6.5","pdf.docinfo.custom.xpressprivate":"%%DocumentProcessColors: Cyan Magenta Yellow Black\n%%DocumentCustomColors: (Red)\n%%+ (Blue)\n%%CMYKCustomColor: 0 .996 .988 0 (Red)\n%%+ .996 .957 0 0 (Blue)\n%%EndComments","pdf.docinfo.modified":"2007-07-10T19:58:04Z","pdf.docinfo.producer":"QuarkXPress(tm) 6.5","pdf.encrypted":false,"pdf.hasmarkedcontent":false,"pdf.hasxfa":false,"pdf.hasxmp":true,"pdf.producer":"QuarkXPress(tm) 6.5","pdf.unmappedunicodecharsperpage":["0","13"],"producer":"QuarkXPress(tm) 6.5","xmp.createdate":"2007-07-10T14:59:30Z","xmp.creatortool":"QuarkXPress(tm) 6.5","xmp.metadatadate":"2007-07-10T22:58:04Z","xmp.modifydate":"2007-07-10T22:58:04Z","xmpmm.documentid":"uuid:d684b194-2f1f-11dc-aaed-000393695c02"},"pdf":{"info":{"creationdate_error":"D:20070710145930Z","producer":"QuarkXPress(tm) 6.5","moddate":"D:20070710225804+03'00'","xpressprivate":"%%DocumentProcessColors: Cyan Magenta Yellow Black\n%%DocumentCustomColors: (Red)\n%%+ (Blue)\n%%CMYKCustomColor: 0 .996 .988 0 (Red)\n%%+ .996 .957 0 0 (Blue)\n%%EndComments"},"pdfversion":"4","metadata":{"x__x":["3.1-701"],"createdate":["7/10/2007 2:59:30 PM"],"creatortool":["QuarkXPress(tm) 6.5"],"modifydate":["7/11/2007 12:58:04 AM"],"metadatadate":["7/11/2007 12:58:04 AM"],"producer":["QuarkXPress(tm) 6.5"],"xpressprivate":["%%DocumentProcessColors: Cyan Magenta Yellow Black\n%%DocumentCustomColors: (Red)\n%%+ (Blue)\n%%CMYKCustomColor: 0 .996 .988 0 (Red)\n%%+ .996 .957 0 0 (Blue)\n%%EndComments"],"format":["application/pdf"],"text":["inceleme deneme"],"documentid":["uuid:d684b194-2f1f-11dc-aaed-000393695c02"],"instanceid":["uuid:dfcbc115-2f1f-11dc-aaed-000393695c02"]},"tampered":false,"appendable":false,"cryptomode":-1},"sha256":"5D3A69A13289C0DD5DB85C0EB144EF3859C7CC353CD10BE8E34B4B2E2E82D802","clean.language":"tr","clean.title":"inceleme deneme","clean.pageCount":"2","clean.creator":"quarkxpress(tm) 6.5"}