{"file":{"path":"D:\\GOOGLE.PHOTO\\Bilim.ve.Teknik.Dergisi.İndir.42.Yıllık.DVD.Arşivi-oneindir.com\\bilimveteknik\\fscommand\\1988_08_60.pdf","name":"1988_08_60.pdf","ext":".pdf","length":146277,"dir":"D:\\GOOGLE.PHOTO\\Bilim.ve.Teknik.Dergisi.İndir.42.Yıllık.DVD.Arşivi-oneindir.com\\bilimveteknik\\fscommand","creation":"2021-11-30T00:09:09","lastaccess":"2021-11-30T02:05:19","lastwrite":"2012-11-29T19:13:32"},"hash":{"md5":"F48D7596FC1F327C9285264C371D8911","sha1":"E95D55CA0BC31A3FD7612A2CD857F8010FC2BF53"},"tika":{"content-type":"application/pdf","creation-date":"2002-10-17T11:48:11","last-modified":"2012-11-29T13:13:32Z","last-save-date":"2012-11-29T13:13:32Z","x-parsed-by":["org.apache.tika.parser.DefaultParser","org.apache.tika.parser.pdf.PDFParser"],"access_permission.assemble_document":true,"access_permission.can_modify":true,"access_permission.can_print":true,"access_permission.can_print_degraded":true,"access_permission.extract_content":true,"access_permission.extract_for_accessibility":true,"access_permission.fill_in_form":true,"access_permission.modify_annotations":true,"created":"2002-10-17T11:48:11","date":"2012-11-29T13:13:32Z","dc.format":"application/pdf; version=1.4","dcterms.created":"2002-10-17T11:48:11Z","dcterms.modified":"2012-11-29T13:13:32Z","meta.creation-date":"2002-10-17T11:48:11Z","meta.save-date":"2012-11-29T13:13:32Z","modified":"2012-11-29T13:13:32Z","pdf.pdfversion":"1.4","pdf.charsperpage":"0","pdf.docinfo.created":"2002-10-17T11:48:11Z","pdf.docinfo.creator_tool":"Adobe Photoshop 6.0","pdf.docinfo.modified":"2012-11-29T13:13:32Z","pdf.docinfo.producer":"Adobe Photoshop for Macintosh","pdf.encrypted":false,"pdf.hasmarkedcontent":false,"pdf.hasxfa":false,"pdf.hasxmp":true,"pdf.producer":"Adobe Photoshop for Macintosh","pdf.unmappedunicodecharsperpage":"0","producer":"Adobe Photoshop for Macintosh","xmp.createdate":"2002-10-17T14:48:11Z","xmp.creatortool":"Adobe Photoshop 6.0","xmp.metadatadate":"2012-11-29T15:13:32Z","xmp.modifydate":"2012-11-29T15:13:32Z","xmpmm.documentid":"uuid:8bf560e1-4ffa-ad45-9114-7c2cceea7758"},"pdf":{"info":{"creationdate_error":"D:20021017144811+03'00'","moddate":"D:20121129151332+02'00'","producer":"Adobe Photoshop for Macintosh"},"pdfversion":"4","metadata":{"x__x":["Adobe XMP Core 5.2-c001 63.139439, 2010/09/27-13:37:26        "],"createdate":["10/17/2002 4:48:11 PM"],"creatortool":["Adobe Photoshop 6.0"],"modifydate":["11/29/2012 5:13:32 PM"],"metadatadate":["11/29/2012 5:13:32 PM"],"producer":["Adobe Photoshop for Macintosh"],"format":["application/pdf"],"documentid":["uuid:8bf560e1-4ffa-ad45-9114-7c2cceea7758"],"instanceid":["uuid:56c7f9c1-dba0-514c-8cdf-43f192178cc6"]},"tampered":false,"appendable":false,"cryptomode":-1},"sha256":"8E2830824740E580BB682EDBCCB61BF61BE528A958F1BF4B3B588A29B37AEEC5","clean.pageCount":"1","clean.creator":"adobe photoshop 6.0"}