{"file":{"path":"E:\\DOCUMENT\\DVD\\DVD-032\\Collins_A.A._Clinical_Drug_Therapy_(2003)(en)(1072s)\\Clinical Drug Therapy\\Ch55.pdf","name":"Ch55.pdf","ext":".pdf","length":191141,"dir":"E:\\DOCUMENT\\DVD\\DVD-032\\Collins_A.A._Clinical_Drug_Therapy_(2003)(en)(1072s)\\Clinical Drug Therapy","creation":"2021-05-11T14:45:46","lastaccess":"2021-05-11T15:05:45","lastwrite":"2005-07-22T00:00:00"},"hash":{"md5":"73418B4BC4D7C43B4C6787095706BB3A","sha1":"FFD33257DCE3C6BFCC1F29003A8A56439020E821"},"tika":{"content-type":"application/pdf","creation-date":"2003-04-23T11:42:06","last-modified":"2003-04-24T16:29:35Z","last-save-date":"2003-04-24T16:29:35Z","x-parsed-by":["org.apache.tika.parser.DefaultParser","org.apache.tika.parser.pdf.PDFParser"],"access_permission.assemble_document":true,"access_permission.can_modify":true,"access_permission.can_print":true,"access_permission.can_print_degraded":true,"access_permission.extract_content":true,"access_permission.extract_for_accessibility":true,"access_permission.fill_in_form":true,"access_permission.modify_annotations":true,"created":"2003-04-23T11:42:06","date":"2003-04-24T16:29:35Z","dc.format":"application/pdf; version=1.2","dcterms.created":"2003-04-23T11:42:06Z","dcterms.modified":"2003-04-24T16:29:35Z","meta.creation-date":"2003-04-23T11:42:06Z","meta.save-date":"2003-04-24T16:29:35Z","modified":"2003-04-24T16:29:35Z","pdf.pdfversion":"1.2","pdf.charsperpage":["2774","5309","7220","6215","5892","4990","4483","5392","2925","3196","3579","1749","5377","5192","5504","5257","5661","5662","3791","4160","1484"],"pdf.docinfo.created":"2003-04-23T11:42:06Z","pdf.docinfo.modified":"2003-04-24T16:29:35Z","pdf.docinfo.producer":"Acrobat Distiller 4.05 for Macintosh","pdf.encrypted":false,"pdf.hasmarkedcontent":false,"pdf.hasxfa":false,"pdf.hasxmp":true,"pdf.producer":"Acrobat Distiller 4.05 for Macintosh","pdf.unmappedunicodecharsperpage":["4","0","0","0","0","0","0","0","0","0","0","0","0","0","0","0","0","0","0","0","0"],"producer":"Acrobat Distiller 4.05 for Macintosh","xmp.createdate":"2003-04-23T11:42:06Z","xmp.metadatadate":"2003-04-24T13:29:35Z","xmp.modifydate":"2003-04-24T13:29:35Z"},"pdf":{"info":{"creationdate_error":"D:20030423114206Z","producer":"Acrobat Distiller 4.05 for Macintosh","moddate":"D:20030424132935-03'00'"},"pdfversion":"2","metadata":{"creationdate":["4/23/2003 11:42:06 AM"],"producer":["Acrobat Distiller 4.05 for Macintosh"],"moddate":["4/24/2003 9:29:35 PM"],"createdate":["4/23/2003 11:42:06 AM"],"modifydate":["4/24/2003 9:29:35 PM"],"metadatadate":["4/24/2003 9:29:35 PM"]},"tampered":false,"appendable":false,"cryptomode":-1},"sha256":"9FC8988B67555FDB76E37F29268F6F33C83BECDB88990F5E21A994378FAEF25D","clean.language":"en","clean.pageCount":"21"}