{"file":{"path":"D:\\GOOGLE.PHOTO\\0-0A3818280BEB98182B2BE0B8080B5BCBEBD82077BC8B88B5B977.pdf","name":"0-0A3818280BEB98182B2BE0B8080B5BCBEBD82077BC8B88B5B977.pdf","ext":".pdf","length":148354,"dir":"D:\\GOOGLE.PHOTO","creation":"2021-05-23T16:45:00","lastaccess":"2021-05-26T09:59:34","lastwrite":"2021-05-23T16:45:00"},"hash":{"md5":"F1B2C68EA64396765E672C9B9EEA99DE","sha1":"27A48A4E713CF0749EFB3DCF3D5E2F9785C5A8E0"},"tika":{"content-type":"application/pdf","creation-date":"2000-04-06T02:03:41","keywords":"genius mouse repair schematics diagram","last-modified":"2000-04-06T02:26:28Z","last-save-date":"2000-04-06T02:26:28Z","x-parsed-by":["org.apache.tika.parser.DefaultParser","org.apache.tika.parser.pdf.PDFParser"],"access_permission.assemble_document":true,"access_permission.can_modify":false,"access_permission.can_print":true,"access_permission.can_print_degraded":true,"access_permission.extract_content":true,"access_permission.extract_for_accessibility":true,"access_permission.fill_in_form":true,"access_permission.modify_annotations":false,"cp.subject":"Genius","created":"2000-04-06T02:03:41","date":"2000-04-06T02:26:28Z","dc.format":"application/pdf; version=1.2","dc.subject":"genius mouse repair schematics diagram","dcterms.created":"2000-04-06T02:03:41Z","dcterms.modified":"2000-04-06T02:26:28Z","meta.creation-date":"2000-04-06T02:03:41Z","meta.keyword":"genius mouse repair schematics diagram","meta.save-date":"2000-04-06T02:26:28Z","modified":"2000-04-06T02:26:28Z","pdf.pdfversion":"1.2","pdf.charsperpage":["0","0","0","0","0"],"pdf.docinfo.created":"2000-04-06T02:03:41Z","pdf.docinfo.creator_tool":"Stas Noskov","pdf.docinfo.keywords":"genius mouse repair schematics diagram","pdf.docinfo.modified":"2000-04-06T02:26:28Z","pdf.docinfo.producer":"Amt electronics [http://amt.ural.ru/]","pdf.docinfo.subject":"Genius","pdf.encrypted":true,"pdf.hasmarkedcontent":false,"pdf.hasxfa":false,"pdf.hasxmp":false,"pdf.unmappedunicodecharsperpage":["0","0","0","0","0"],"producer":"Amt electronics [http://amt.ural.ru/]","subject":"Genius","xmp.creatortool":"Stas Noskov"},"sha256":"B305428928A75756395DECFAA34C2B74CDDBB0AFA6087CF8D5B5815E8047BB72","clean.language":"fi","clean.title":"℄䔄㔄㰄䬄 㠄 䀄㔄㰄㸄㴄䈄 㰄䬄䠄㔄㨄 䜀攀渀椀甀猀","clean.pageCount":"5","clean.author":"℄䈄〄㴄㠄䄄㬄〄㈄ ᴄ㸄䄄㨄㸄㈄","clean.creator":"℄䈄〄㴄㠄䄄㬄〄㈄ ᴄ㸄䄄㨄㸄㈄"}