{"file":{"path":"D:\\SHARED\\___AZ_CORPUS\\_BUFFER\\Qaraca_qiz_Konul_Aydin_Nehmetova__Qaraca_qizin_taleyi.pdf","name":"Qaraca_qiz_Konul_Aydin_Nehmetova__Qaraca_qizin_taleyi.pdf","ext":".pdf","length":3762656,"dir":"D:\\SHARED\\___AZ_CORPUS\\_BUFFER","creation":"2017-05-22T03:31:32","lastaccess":"2020-12-17T03:42:11","lastwrite":"2017-05-22T03:31:32"},"hash":{"md5":"84E05F48BAA413B12F98D7FBF565AD79","sha1":"2C62F27924179F8D2BA25E50FB9F107D009A6D15"},"tika":{"content-type":"application/pdf","creation-date":"2016-03-03T08:35:15","last-modified":"2016-03-03T08:35:15","last-save-date":"2016-03-03T08:35:15","x-parsed-by":["org.apache.tika.parser.DefaultParser","org.apache.tika.parser.pdf.PDFParser"],"access_permission.assemble_document":"true","access_permission.can_modify":"true","access_permission.can_print":"true","access_permission.can_print_degraded":"true","access_permission.extract_content":"true","access_permission.extract_for_accessibility":"true","access_permission.fill_in_form":"true","access_permission.modify_annotations":"true","created":"2016-03-03T08:35:15","date":"2016-03-03T08:35:15","dc.format":"application/pdf; version=1.5","dcterms.created":"2016-03-03T08:35:15","dcterms.modified":"2016-03-03T08:35:15","meta.creation-date":"2016-03-03T08:35:15","meta.save-date":"2016-03-03T08:35:15","modified":"2016-03-03T08:35:15","pdf.pdfversion":"2020-01-05T00:00:00","pdf.charsperpage":["153","1304","353","4","2472","2274","2293","2269","2265","2151","2143","2208","2202","2136","1887","2191","2227","1543","1609","1878","2027","1787","1802","2253","1756","1636","1805","1635","1781","1717","7","796","1835","1921","1744","1380","1916","1857","1604","1653","1587","1961","1569","1633","1833","1783","1702","1758","1574","1855","1460","1455","1645","1724","1814","1801","1465","1887","1675","1700","1294","1633","1739","1569","1706","1808","1373","1774","1575","1841","1699","1536","1453","1505","1578","1482","1486","598","8","1809","1902","1621","1617","1874","1694","1500","1671","1770","1768","1510","1556","1773","1647","1425","1707","1797","1361","1674","1671","1708","1867","1385","1721","1741","1513","1325","1737","1522","1485","1758","1845","1403","1668","1790","1626","1340","1657","1620","1450","1133","13","1738","1259","1312","1644","1479","1038","1477","1469","1283","1337","1002","1806","1287","1318","1614","1326","1604","1122","1660","1469","1024","1728","1701","1896","1291","1059","1163","1748","1520","1223","960","1532","1477","1759","1276","1561","1224","1759","1250","1630","1443","1351","1548","1380","1093","7","9","1477","718","41","16"],"pdf.docinfo.created":"2016-03-03T08:35:15","pdf.docinfo.creator_tool":"Microsoft® Word 2010","pdf.docinfo.modified":"2016-03-03T08:35:15","pdf.docinfo.producer":"Microsoft® Word 2010","pdf.encrypted":"false","pdf.hasmarkedcontent":"true","pdf.hasxfa":"false","pdf.hasxmp":"false","pdf.unmappedunicodecharsperpage":["0","0","0","0","0","0","0","0","0","0","0","0","0","0","0","0","0","0","0","0","0","0","0","0","0","0","0","0","0","0","0","0","0","0","0","0","0","0","0","0","0","0","0","0","0","0","0","0","0","0","0","0","0","0","0","0","0","0","0","0","0","0","0","0","0","0","0","0","0","0","0","0","0","0","0","0","0","0","0","0","0","0","0","0","0","0","0","0","0","0","0","0","0","0","0","0","0","0","0","0","0","0","0","0","0","0","0","0","0","0","0","0","0","0","0","0","0","0","0","0","0","0","0","0","0","0","0","0","0","0","0","0","0","0","0","0","0","0","0","0","0","0","0","0","0","0","0","0","0","0","0","0","0","0","0","0","0","0","0","0","0","0","0","0","0","0","0","0","0","0","0","0"],"producer":"Microsoft® Word 2010","xmp.creatortool":"Microsoft® Word 2010"},"pdf":{"info":{"creationdate":"D:20160303123515+04'00'","moddate":"D:20160303123515+04'00'","producer":"Microsoft® Word 2010"},"pdfversion":"5","tampered":false,"appendable":false,"cryptomode":-1},"sha256":"BC9FBA10686F6D95087FC9091A5DB9BB4B54FC1D2A5D324A41FC275FB372E7CC","clean.language":"ru,tr","clean.pageCount":"172","clean.author":"s-admin","clean.creator":"[\"s-admin\",\"microsoft® word 2010\"]"}