{"file":{"path":"D:\\CRAWLING\\achiqkitab.aztc.gov.az\\198.pdf","name":"198.pdf","ext":".pdf","length":4332602,"dir":"D:\\CRAWLING\\achiqkitab.aztc.gov.az","creation":"2020-08-22T15:59:45","lastaccess":"2020-12-25T17:19:07","lastwrite":"2020-08-22T15:59:47"},"hash":{"md5":"5705FE4C02FDA1C302AB621675AA5764","sha1":"4DE3B8683947121662FC9BB7CD365ABD6AFD35C3"},"tika":{"content-type":"application/pdf","creation-date":"2010-07-07T14:52:40","last-modified":"2010-07-07T10:53:52","last-save-date":"2010-07-07T10:53:52","x-parsed-by":["org.apache.tika.parser.DefaultParser","org.apache.tika.parser.pdf.PDFParser"],"access_permission.assemble_document":"true","access_permission.can_modify":"true","access_permission.can_print":"true","access_permission.can_print_degraded":"true","access_permission.extract_content":"true","access_permission.extract_for_accessibility":"true","access_permission.fill_in_form":"true","access_permission.modify_annotations":"true","created":"2010-07-07T14:52:40","date":"2010-07-07T10:53:52","dc.format":"application/pdf; version=1.2","dcterms.created":"2010-07-07T14:52:40","dcterms.modified":"2010-07-07T10:53:52","meta.creation-date":"2010-07-07T14:52:40","meta.save-date":"2010-07-07T10:53:52","modified":"2010-07-07T10:53:52","pdf.pdfversion":"2020-01-02T00:00:00","pdf.charsperpage":["0","0","0","0","0","0","0","0","0","0","0","0","0","0","0","0","0","0","0","0","0","0","0","0","0","0","0","0","0","0","0","0","0","0","0","0","0","0","0","0","0","0","0","0","0","0","0","0","0","0","0","0","0","0","0","0","0","0","0","0","0","0","0","0","0","0","0","0","0","0","0","0","0","0","0","0","0","0","0","0","0","0","0","0","0","0","0","0","0","0","0","0","0","0","0","0","0","0","0","0","0","0","0","0","0","0","0","0","0","0","0","0","0","0","0","0","0","0","0","0","0","0","0","0","0"],"pdf.docinfo.created":"2010-07-07T14:52:40","pdf.docinfo.modified":"2010-07-07T10:53:52","pdf.docinfo.producer":"ABBYY FineReader 8.0 Professional Edition","pdf.encrypted":"false","pdf.hasmarkedcontent":"false","pdf.hasxfa":"false","pdf.hasxmp":"false","pdf.unmappedunicodecharsperpage":["0","0","0","0","0","0","0","0","0","0","0","0","0","0","0","0","0","0","0","0","0","0","0","0","0","0","0","0","0","0","0","0","0","0","0","0","0","0","0","0","0","0","0","0","0","0","0","0","0","0","0","0","0","0","0","0","0","0","0","0","0","0","0","0","0","0","0","0","0","0","0","0","0","0","0","0","0","0","0","0","0","0","0","0","0","0","0","0","0","0","0","0","0","0","0","0","0","0","0","0","0","0","0","0","0","0","0","0","0","0","0","0","0","0","0","0","0","0","0","0","0","0","0","0","0"],"producer":"ABBYY FineReader 8.0 Professional Edition"},"pdf":{"info":{"moddate":"D:20100707145352+04'00'","producer":"ABBYY FineReader 8.0 Professional Edition","creationdate":"D:20100707145240"},"pdfversion":"2","tampered":false,"appendable":false,"cryptomode":-1},"sha256":"BD0C1BF3E5D272FF8CBD8E0E55D2163D0698A0D87297F8116C455CBE24760CA5","clean.pageCount":"125"}