{"file":{"path":"C:\\Users\\habib\\Downloads\\Takeout\\Drive\\The-Courage-Tree-Diane-Chamberlain(www.ebook-d.epub","name":"The-Courage-Tree-Diane-Chamberlain(www.ebook-d.epub","ext":".epub","length":589956,"dir":"C:\\Users\\habib\\Downloads\\Takeout\\Drive","creation":"2021-06-12T18:17:23","lastaccess":"2021-06-12T18:24:44","lastwrite":"2017-03-05T05:58:44"},"hash":{"md5":"51C8834BF36AB702E587824C84DA81C5","sha1":"097483911B96816094D6A60520C2402E32287D3A"},"tika":{"content-type":"application/epub+zip","creation-date_error":"2001","x-parsed-by":["org.apache.tika.parser.DefaultParser","org.apache.tika.parser.epub.EpubParser"],"contributor":"Diane Chamberlain","dc.contributor":"Diane Chamberlain","dc.identifier":"9781426830891","dc.publisher":"MIRA","dc.rights":"Copyright 2001 by Diane Chamberlain","dcterms.created":"2001","identifier":"9781426830891","meta.creation-date":"2001","publisher":"MIRA","rights":"Copyright 2001 by Diane Chamberlain"},"epub":{"title":"The Courage Tree","authors":["Diane Chamberlain"],"doctitle":"The Courage Tree","meta":{"dtb.uid":"c98702cc-1def-4789-9366-18d8bdf83710","dtb.depth":"1","dtb.totalpagecount":"0","dtb.maxpagenumber":"0"},"epubversion":2,"titles":["The Courage Tree"],"publishers":["MIRA"],"creators":[{"text":"Diane Chamberlain"}],"contributors":[{"text":"Diane Chamberlain"}],"metas":[{"name":"cover","text":"my-cover-image"}]},"sha256":"C42CEFAE184F69BBA71F16FE17AE6895F8C9D43B5125E51026FCC6DD1DD7E680","clean.language":"en,[\r\n  \"en\"\r\n]","clean.title":"the courage tree","clean.author":"diane chamberlain","clean.creator":"diane chamberlain"}