{"file":{"path":"E:\\Downloads\\Yandex\\BCP KUTUPHANE\\Tıp Bilimi-\\SLAYTLAR\\ERSAN-KARD-YO\\EKG-yestus.ppt","name":"EKG-yestus.ppt","ext":".ppt","length":3961856,"dir":"E:\\Downloads\\Yandex\\BCP KUTUPHANE\\Tıp Bilimi-\\SLAYTLAR\\ERSAN-KARD-YO","creation":"2021-12-14T12:19:29","lastaccess":"2021-12-14T22:52:30","lastwrite":"2021-12-14T12:19:34"},"hash":{"md5":"34F59F06712B7641115DF95535CFE0A6","sha1":"B119E628E3B8C75407E17F6E2B72DA569421848B"},"tika":{"application-name":"Microsoft PowerPoint","company":"Home","content-type":"application/vnd.ms-powerpoint","creation-date":"2005-07-08T22:11:59","edit-time":"383332710000","last-author":"Administrator","last-modified":"2005-08-01T09:40:17Z","last-save-date":"2005-08-01T09:40:17Z","revision-number":"27","slide-count":"64","word-count":"1176","x-parsed-by":["org.apache.tika.parser.DefaultParser","org.apache.tika.parser.microsoft.OfficeParser"],"cp.revision":"27","date":"2005-08-01T09:40:17Z","dcterms.created":"2005-07-08T22:11:59Z","dcterms.modified":"2005-08-01T09:40:17Z","extended-properties.application":"Microsoft PowerPoint","extended-properties.company":"Home","meta.creation-date":"2005-07-08T22:11:59Z","meta.last-author":"Administrator","meta.save-date":"2005-08-01T09:40:17Z","meta.slide-count":"64","meta.word-count":"1176","modified":"2005-08-01T09:40:17Z"},"sha256":"D4885712D6935C4D5482FE219CA30E7B13DAB1F0CDC3A1B0D3A485A67C8D2702","clean.language":"tr","clean.title":"powerpoint presentation","clean.pageCount":"64","clean.author":"ersan","clean.creator":"ersan"}