{"file":{"path":"D:\\GOOGLE.PHOTO\\manybooks\\121642\\The-Chouans.rtf","name":"The-Chouans.rtf","ext":".rtf","length":932683,"dir":"D:\\GOOGLE.PHOTO\\manybooks\\121642","creation":"2021-07-09T20:48:02","lastaccess":"2021-07-12T17:09:09","lastwrite":"2021-07-09T20:48:02"},"hash":{"md5":"BA0B60F75618E8C21CBCE78BE5EDC0AE","sha1":"16FDC102CA566C9BDB5230400C80BF4FCC522782"},"tika":{"content-type":"application/rtf","x-parsed-by":["org.apache.tika.parser.DefaultParser","org.apache.tika.parser.rtf.RTFParser"]},"sha256":"DD11B5EF9233E233C987E2023E79611D7FF9055BBA2C6D781469B87961994130","clean.language":"en","clean.title":"the chouans","clean.author":"unknown","clean.creator":"unknown"}