{"file":{"path":"D:\\GOOGLE.PHOTO\\New\\Pdf Kitap\\Pdf Kitap\\Turgenyev - Bahar Seli.pdf","name":"Turgenyev - Bahar Seli.pdf","ext":".pdf","length":9077165,"dir":"D:\\GOOGLE.PHOTO\\New\\Pdf Kitap\\Pdf Kitap","creation":"2021-12-14T20:03:55","lastaccess":"2021-12-14T20:13:14","lastwrite":"2021-12-14T15:21:06"},"hash":{"md5":"790118FA5D1569C79C69DAB14AE8EAFF","sha1":"1C128DEAB7F946640555B0D6B527FEEA645940AC"},"tika":{"content-type":"application/pdf","creation-date":"2015-10-15T17:14:35","last-modified":"2015-10-15T17:37:27Z","last-save-date":"2015-10-15T17:37:27Z","x-parsed-by":["org.apache.tika.parser.DefaultParser","org.apache.tika.parser.pdf.PDFParser"],"access_permission.assemble_document":true,"access_permission.can_modify":true,"access_permission.can_print":true,"access_permission.can_print_degraded":true,"access_permission.extract_content":true,"access_permission.extract_for_accessibility":true,"access_permission.fill_in_form":true,"access_permission.modify_annotations":true,"created":"2015-10-15T17:14:35","date":"2015-10-15T17:37:27Z","dc.format":"application/pdf; version=1.6","dcterms.created":"2015-10-15T17:14:35Z","dcterms.modified":"2015-10-15T17:37:27Z","meta.creation-date":"2015-10-15T17:14:35Z","meta.save-date":"2015-10-15T17:37:27Z","modified":"2015-10-15T17:37:27Z","pdf.pdfversion":"1.6","pdf.charsperpage":["0","107","134","1289","1836","1542","1561","1487","1298","1486","1471","1328","1390","1749","1396","1722","1765","1500","1268","1505","1486","1189","1340","1436","1822","1454","1309","1679","1500","1679","1322","1699","1417","1605","1655","1408","1680","1650","1673","1744","1574","1662","1567","1691","1679","1524","1298","1283","1244","1195","1629","1407","1515","1317","1531","1504","1346","1515","1348","1403","1378","1273","1744","1548","1479","1236","1613","1536","1294","1248","1488","1479","1275","1417","1188","1270","1297","1458","1368","1521","1313","1158","1536","1779","1324","1371","1132","1397","1303","1431","1634","1429","1545","1356","1621","1582","1524","1455","1351","1438","1219","1470","1180","1622","1391","1108","1343","1348","1429","1319","1408","1213","1265","1440","1300","1658","1658","1329","1105","1064","1320","1565","1460","1313","1591","1445","1520","1263","1417","1418","1429","1280","1754","1422","1425","1338","1074","1670","1500","1432","1565","1551","1366","1623","1352","1649","1235","1446","1495","1647","1317","1262","1476","1376","1288","1221","1316","1454","1349","1681","1641","1361","1658","1752","1601","863","1513","1763","0","0"],"pdf.docinfo.created":"2015-10-15T17:14:35Z","pdf.docinfo.modified":"2015-10-15T17:37:27Z","pdf.docinfo.producer":"Adobe Acrobat Pro 11.0.8 Paper Capture Plug-in with ClearScan","pdf.encrypted":false,"pdf.hasmarkedcontent":false,"pdf.hasxfa":false,"pdf.hasxmp":true,"pdf.producer":"Adobe Acrobat Pro 11.0.8 Paper Capture Plug-in with ClearScan","pdf.unmappedunicodecharsperpage":["0","0","0","0","0","0","0","0","0","0","0","0","0","0","0","0","0","0","0","0","0","0","0","0","0","0","0","0","0","0","0","0","0","0","0","0","0","0","0","0","0","0","0","0","0","0","0","0","0","0","0","0","0","0","0","0","0","0","0","0","0","0","0","0","0","0","0","0","0","0","0","0","0","0","0","0","0","0","0","0","0","0","0","0","0","0","0","0","0","0","0","0","0","0","0","0","0","0","0","0","0","0","0","0","0","0","0","0","0","0","0","0","0","0","0","0","0","0","0","0","0","0","0","0","0","0","0","0","0","0","0","0","0","0","0","0","0","0","0","0","0","0","0","0","0","0","0","0","0","0","0","0","0","0","0","0","0","0","0","0","0","0","0","0","0","0","0","0","0","0"],"producer":"Adobe Acrobat Pro 11.0.8 Paper Capture Plug-in with ClearScan","xmp.createdate":"2015-10-15T17:14:35Z","xmp.metadatadate":"2015-10-15T20:37:27Z","xmp.modifydate":"2015-10-15T20:37:27Z","xmpmm.documentid":"uuid:48409e04-3929-47e5-9406-31c1aa81bbe5"},"pdf":{"info":{"creationdate_error":"D:20151015171435Z","moddate":"D:20151015203727+03'00'","producer":"Adobe Acrobat Pro 11.0.8 Paper Capture Plug-in with ClearScan"},"pdfversion":"6","metadata":{"x__x":["Adobe XMP Core 5.4-c005 78.147326, 2012/08/23-13:03:03        "],"createdate":["10/15/2015 5:14:35 PM"],"modifydate":["10/15/2015 10:37:27 PM"],"metadatadate":["10/15/2015 10:37:27 PM"],"producer":["Adobe Acrobat Pro 11.0.8 Paper Capture Plug-in with ClearScan"],"format":["application/pdf"],"documentid":["uuid:48409e04-3929-47e5-9406-31c1aa81bbe5"],"instanceid":["uuid:b25b05d8-c75e-4290-a37d-389b7ce4c117"]},"tampered":false,"appendable":false,"cryptomode":-1},"sha256":"F233F460B722931FAF6A09EE27C2ED0C412E7B387E5E42B9EEC709DDB3239507","clean.language":"tr","clean.pageCount":"170"}